Workbook

Sheet Candidates
A1: ID | B1: Candidate | C1: Category | D1: Look line | E1: Strongest signal | F1: Signal source | G1: Signal URL | H1: Signal date | I1: Signal verified? | J1: Other signals | K1: Typical retail (seen) | L1: Typical supplier cost (seen) | M1: IP risk | N1: Battery or skin? | O1: Why it will pin | P1: Decision | Q1: Reject reason
A2: C001 | B2: Satin sleep bonnet (adjustable tie band, pink/blush) | C2: beauty-selfcare | D2: The Pink Bedtime Routine / Sunday Reset Self-Care list | E2: Keyword page 'hair bonnets' shows product card with 351.2K sold | F2: TikTok Shop | G2: https://shop.tiktok.com/us/k/hair-bonnets | H2: 2026-09 (search snippet) | I2: seen in snippet (aggregated keyword page; sold count belongs to a product card on that page, exact SKU not confirmed) | J2: TikTok Shop: Keyword page 'satin bonnet for sleep leopard' shows 4.4K sold (https://shop.tiktok.com/us/k/satin-bonnet-for-sleep-leopard) | TikTok Shop: Keyword page 'satin bonnet before and after' shows product cards from 1.3K to 179K sold (https://shop.tiktok.com/us/k/satin-bonnet-before-and-after) | TikTok Shop: Keyword page 'satin vs silk bonnet' shows a card with 2.2M sold (https://shop.tiktok.com/us/k/satin-vs-silk-bonnet) | AliExpress: Two '2026 New' satin bonnet listings live (1005010652557849, 1005010511012337); order counts not visible in snippet (https://www.aliexpress.com/item/1005010652557849.html) | K2: TikTok Shop under $5 to $30+ per snippet; branded Bounce Curl bonnet $22.00 with 2.2K sold (https://shop.tiktok.com/us/k/bounce-curl-satin-bonnet) | L2: unknown (AliExpress listing prices not shown in snippet) | M2: none (avoid K-pop / character-print variants seen on TikTok Shop) | N2: none | O2: A blush satin bonnet with a bow is the hero of every pink 'night routine' flat lay and reads as self-care, not hair care. | P2: BANK Q14
A3: C002 | B3: Spa headband + wrist towel set (bow / coquette style, pink) | C3: beauty-selfcare | D3: The Pink Skincare Shelf / Everything Shower list | E3: Keyword page 'spa headband and wristband' shows product card with 13.7K sold at $2.11 (was $4.39, -52%) | F3: TikTok Shop | G3: https://shop.tiktok.com/us/k/spa-headband-and-wristband | H3: 2026-09 (search snippet) | I3: seen in snippet | J3: TikTok Shop: Keyword page 'spa headband' shows card with 43 sold at $3.28 (was $7.99) (https://shop.tiktok.com/us/k/spa-headband) | K3: TikTok Shop $2.11 to $7.99 (snippet); blush set listing by Gnarley Charley https://shop.tiktok.com/us/pdp/blush-spa-headband-wristband-set-by-gnarley-charley-hair-accessory/1729441297081799237 | L3: unknown | M3: none (skip 'cute bear' / character variants) | N3: none (worn on hair/wrists, not a cosmetic) | O3: Ultra-low price, bow-topped, and the first thing on screen in every GRWM skincare video. | P3: BANK E17
A4: C003 | B4: Travel makeup 'vanity bag' / large-capacity cosmetic case (pink) | C4: beauty-selfcare | D4: The Pink Weekend Trip / Carry-On Essentials list | E4: 'Vanity Bag' approx. 206K searches/month, up 66% YoY (quoted by CJ Dropshipping blog citing Google Trends) | F4: Google Trends | G4: https://cjdropshipping.com/blogs/selling-strategies/google-trends-products | H4: 2026 (CJ blog) | I4: seen in snippet (secondary source quoting Google Trends; not seen directly on trends.google.com) | J4: TikTok Shop: Keyword page 'pink makeup case' shows card with 51 sold at $13.80 (https://shop.tiktok.com/us/k/pink-makeup-case) | K4: TikTok Shop $13.80 to $16.19 (snippet); Amazon Best Sellers Cosmetic Travel Cases page https://www.amazon.com/Best-Sellers-Cosmetic-Travel-Cases/zgbs/beauty/11062811 (ranks not visible) | L4: unknown (CJ product page price not in snippet) | M4: none (avoid 'Saie', 'Rhode', 'Hailey Bieber' branded search terms seen on TikTok Shop) | N4: none | O4: Open-flat pink vanity case with adjustable dividers is the 'what's in my travel bag' pin format that gets saved for the next trip. | P4: BANK E13
A5: C004 | B5: Pink feather-trim pajama set | C5: beauty-selfcare | D5: The Pink Bedtime Routine / Bridal-Shower Loungewear list | E5: Keyword page 'pink feather pajamas' shows card with 3.4K sold at $15.40 (was $19.49, -21%) | F5: TikTok Shop | G5: https://shop.tiktok.com/us/k/pink-feather-pajamas | H5: 2026-09 (search snippet) | I5: seen in snippet | J5: TikTok Shop: Keyword page 'pajama sets' shows card with 249 sold at $70.20 (limited time deal) (https://shop.tiktok.com/us/k/pajama-sets) | K5: TikTok Shop $15.40 to $26.54 (snippet) | L5: unknown | M5: none | N5: none | O5: Feather cuffs in baby pink are the 'Legally Blonde at home' look; it doubles as a gifting pin. | P5: BANK E21
A6: C005 | B6: Pink robe with fur/feather trim | C6: beauty-selfcare | D6: The Pink Bedtime Routine / Getting-Ready Robe list | E6: Keyword page 'pink robe with fur trim' shows card with 592 sold at $41.36 | F6: TikTok Shop | G6: https://shop.tiktok.com/us/k/pink-robe-with-fur-trim | H6: 2026-09 (search snippet) | I6: seen in snippet | J6: TikTok Shop: Keyword page 'fluffy robe' shows card with 11 sold, $6.61 to $9.45 (-30%) (https://shop.tiktok.com/us/k/fluffy-robe) | K6: TikTok Shop $35 to $88 for premium plush (snippet); 'The Viral Robe' pink https://shop.tiktok.com/us/pdp/soliana-signature-robe-by-viral-robe-pink-womens-loungewear/1729481808994734198 | L6: unknown | M6: none (do not market as 'Viral Robe' brand) | N6: none | O6: The pink getting-ready robe is the bridal, birthday and Sunday-reset pin all in one. | P6: BANK E23
A7: C006 | B7: Puffy / fluffy pink slippers and slides | C7: beauty-selfcare | D7: The Pink Bedtime Routine / Cozy Pink Home list | E7: Keyword page 'puffy slides' shows card with 5.7K sold at $17.28 (was $24.34, -29%) | F7: TikTok Shop | G7: https://shop.tiktok.com/us/k/puffy-slides | H7: 2026-09 (search snippet) | I7: seen in snippet | J7: TikTok Shop: Keyword page 'puffy slippers' shows card with 3.6K sold at $30.98 (flash sale) (https://shop.tiktok.com/us/k/puffy-slippers) | TikTok Shop: Keyword page 'pluffi slippers' shows card with 7.6K sold at $49.99 (branded, reference only) (https://shop.tiktok.com/us/k/pluffi-slippers) | K7: TikTok Shop $17.28 to $49.99 (snippet) | L7: unknown | M7: note: 'Pluffi' is a brand; sell generic puffy slides only, never as a dupe | N7: none | O7: Pillow-puffy pink slides are the shoe in every pink dorm and apartment flat lay. | P7: BANK E19
A8: C007 | B8: Silk / satin sleep mask (pink) | C8: beauty-selfcare | D8: The Pink Bedtime Routine / Travel Self-Care list | E8: Keyword page 'silk blindfold' shows card with 4.2K sold at $39.00 | F8: TikTok Shop | G8: https://shop.tiktok.com/us/k/silk-blindfold | H8: 2026-09 (search snippet) | I8: seen in snippet | K8: TikTok Shop up to $39 for mulberry silk (snippet); pink mulberry silk mask listing https://shop.tiktok.com/us/pdp/silk-sleep-mask-by-litbear-22-momme-mulberry-silk-eye-mask-for-comfort/1729436920505209656 | L8: unknown | M8: none (avoid 'Slip' brand references) | N8: note: touches face but is a textile accessory, not a cosmetic; no battery | O8: A pink silk mask with a bow is the cheapest 'luxury' item in the bedtime pin set. | P8: BANK E20
A9: C008 | B9: Hot pink desk / vanity organiser (multi-compartment) | C9: beauty-selfcare | D9: The Law School Desk Setup, All Pink / Pink Vanity Organisation list | E9: Keyword page 'hot pink desk organizer ideas' shows card with 7.7K sold at $10.99 (was $44.00, -75%) | F9: TikTok Shop | G9: https://shop.tiktok.com/us/k/hot-pink-desk-organizer-ideas | H9: 2026-09 (search snippet) | I9: seen in snippet | K9: TikTok Shop $10.99 (snippet) | L9: unknown | M9: none | N9: none | O9: Crosses over office and vanity: one hot-pink organiser that works on a desk or dresser gets saved to both boards. | P9: BANK E16
A10: C009 | B10: Glitter / pink makeup brush holder cup | C10: beauty-selfcare | D10: The Pink Vanity Organisation list | E10: Keyword page 'glitter makeup holder' shows card with 1.3K sold at $12.30 | F10: TikTok Shop | G10: https://shop.tiktok.com/us/k/glitter-makeup-holder | H10: 2026-09 (search snippet) | I10: seen in snippet | J10: TikTok Shop: Keyword page 'silicone makeup brush case' shows card with 170 sold at $5.45 (was $8.39, -35%) (https://shop.tiktok.com/us/k/silicone-makeup-brush-case) | K10: TikTok Shop $5.45 to $12.30 (snippet) | L10: AliExpress pearl acrylic brush holder with lid listed at US $11.50 https://www.aliexpress.com/item/M-makeup-brush-holder-pearls-organizer-acrylic-plastic-clear-cosmetic-brush-white-pink-pearls-storage-box/32954351202.html | M10: none | N10: none | O10: Pearl-filled or glitter brush cups are the detail shot in every pink vanity tour. | P10: BANK E14
A11: C010 | B11: Acrylic perfume / vanity display tray (2-tier or mirrored) | C11: beauty-selfcare | D11: The Pink Vanity Organisation / Perfume Shelf list | E11: Keyword page 'perfume vanity tray organizer' shows product cards with 25, 29, 55 and 1.5K sold | F11: TikTok Shop | G11: https://shop.tiktok.com/us/k/perfume-vanity-tray-organizer | H11: 2026-09 (search snippet) | I11: seen in snippet | J11: TikTok Shop: NiHome 2-Tier Acrylic Perfume Display Stand listing shows 173 sold (https://shop.tiktok.com/us/pdp/acrylic-perfume-display-stand-by-nihome-2-tier-organizer-for-vanity/1730302818778518451) | TikTok Shop: Keyword page 'perfume tray wooden' shows cards from 4 to 5,000 sold, one at 260 sold (https://shop.tiktok.com/us/k/perfume-tray-wooden) | TikTok Shop: Keyword page 'perfume tray' shows cards with 35, 195 and 461.7K sold (https://shop.tiktok.com/us/k/perfume-tray) | K11: unknown (prices not in snippet) | L11: unknown | M11: none | N11: none (tray only, no perfume) | O11: The perfume-tray shot is the most-saved vanity pin format; a pink or gold-trim tray sells the styling, not the scent. | P11: BANK E15
A12: C011 | B12: Heatless satin curling rod / headband set (pink) | C12: beauty-selfcare | D12: The Pink Bedtime Routine / Heatless Blowout list | E12: Keyword page 'home-bargains-heatless-curlers' shows card with 64 sold at $3.67 (was $19.99) | F12: TikTok Shop | G12: https://shop.tiktok.com/us/k/home-bargains-heatless-curlers | H12: 2026-09 (search snippet) | I12: seen in snippet | J12: TikTok Shop: Keyword page 'best heatless curle' shows card with 39 sold at $22.98 (https://shop.tiktok.com/us/k/best-heatless-curle) | TikTok Shop: Keyword page 'heatless curlers for short hair' shows card with 23 sold at $6.12 (https://shop.tiktok.com/us/k/heatless-curlers-for-short-hair) | Amazon Best Sellers: Amazon listing titled '2026 New Upgraded Eight Claw Design Satin Heatless Curling Rod' live (rank not in snippet) (https://www.amazon.com/clp/B0D4LWJT8P) | K12: TikTok Shop $3.67 to $22.98 (snippet); Kitsch branded set on TikTok Shop for reference https://shop.tiktok.com/us/pdp/kitsch-heatless-curling-rod-4pcs-jumbo-satin-hair-curlers-for-all-types/1729433840720515122 | L12: unknown (AliExpress prices not shown) | M12: note: avoid 'Kitsch' and 'BT21 x Kitsch' branded sets; generic satin rod only | N12: none | O12: Sold counts on TikTok are modest per SKU, but the pink 9-piece bundle (rod + bonnet + scrunchie + mask) is a ready-made 'heatless night routine' pin. | P12: BANK E22
A13: C012 | B13: Jewelry box / bracelet organiser (pink velvet or felt) | C13: beauty-selfcare | D13: The Pink Vanity Organisation / Gifting for Her list | E13: Keyword page 'jewellery boxes' shows card with 464 sold at -77% limited time deal | F13: TikTok Shop | G13: https://shop.tiktok.com/us/k/jewellery-boxes | H13: 2026-09 (search snippet) | I13: seen in snippet | K13: unknown (deal price not in snippet); pink felt bracelet box listing https://shop.tiktok.com/us/pdp/p6nk-jewelry-organizer-real-pink-felt-black-exterior/1732046163444142193 | L13: unknown | M13: none (skip 'Pandora' branded boxes seen at 79 sold) | N13: none | O13: A pink velvet jewelry box is the vanity pin that also gets saved as a gift idea. | P13: REJECT | Q13: Numeric signal exists but weaker than the 40 kept, or it duplicates a kept product in the same look.
A14: C013 | B14: Silicone makeup sponge holder (pink) | C14: beauty-selfcare | D14: The Pink Vanity Organisation list | E14: Keyword page 'makeup sponges holders' related listings show sold quantities ranging from 1 to 11.7K | F14: TikTok Shop | G14: https://shop.tiktok.com/us/k/makeup-sponges-holders | H14: 2026-09 (search snippet) | I14: unverified: 11.7K figure appeared in a related-search card; exact SKU not identified | K14: unknown; pink silicone holder listing https://shop.tiktok.com/us/pdp/silicone-makeup-sponge-holder-portable-durable-pink/1731600449249513992 | L14: unknown | M14: none | N14: none | O14: Tiny, cheap, pink, and solves the 'where do I dry my sponge' problem shown in every vanity tour. | P14: REJECT | Q14: Numeric signal exists but weaker than the 40 kept, or it duplicates a kept product in the same look.
A15: C014 | B15: Covered acrylic makeup organiser (dustproof lid) | C15: beauty-selfcare | D15: The Pink Vanity Organisation list | E15: Keyword page 'covered makeup organizer' shows card with 45 sold at $13.98 (was $28.99, -52%) | F15: TikTok Shop | G15: https://shop.tiktok.com/us/k/covered-makeup-organizer | H15: 2026-09 (search snippet) | I15: seen in snippet | K15: TikTok Shop $13.98 (snippet); Amazon Best Sellers Cosmetic Display Cases page https://www.amazon.com/Best-Sellers-Cosmetic-Display-Cases/zgbs/beauty/13861693011 (ranks not visible) | L15: AliExpress rotating pink acrylic organiser listed at US $179.98 (outlier, not a dropship price) https://www.aliexpress.com/item/Hot-Sale-Ailla-Pink-Acrylic-Makeup-Organizer-Rotating-Cosmetic-Tool-Cases-Jewelry-Storage-Holder/32802626744.html | M15: none | N15: none | O15: Clear-with-pink-lid organisers are the base layer of every pink vanity pin; weak sold signal so far, listed for completeness. | P15: BANK E18
A16: C015 | B16: Claw clip (pearl / rhinestone / jelly pink) | C16: beauty-selfcare | D16: The Girly Professional Hair Accessories list | E16: Keyword page 'claw clamps' shows card with 10 sold at $4.99 (limited time deal) | F16: TikTok Shop | G16: https://shop.tiktok.com/us/k/claw-clamps | H16: 2026-09 (search snippet) | I16: seen in snippet (weak) | J16: other: Who What Wear 2026: pearl and rhinestone claw clips and jelly claw clips called out as 2026 trend (no number) (https://www.whowhatwear.com/beauty/hair/hair-accessories-trends-2026) | K16: TikTok Shop $4.99 (snippet); jumbo fuchsia marble acetate clip listing https://shop.tiktok.com/us/pdp/hair-claw-by-ari-mae-jumbo-5-1-inch-fuchsia-marble-durable-acetate/1729403242832826423 | L16: unknown | M16: none | N16: none | O16: The office-to-gym pink claw clip is the low-cost add-on in every 'girly professional' desk pin. | P16: REJECT | Q16: Numeric signal exists but weaker than the 40 kept, or it duplicates a kept product in the same look.
A17: C016 | B17: Satin hair bow clip (oversized, pink) | C17: beauty-selfcare | D17: The Girly Professional Hair Accessories / Coquette Bow list | E17: Pinterest Predicts 2026 coverage: 'bows and ribbons remain en vogue', preppy headbands and 'wonky' clips named (no number in snippet) | F17: Pinterest Predicts | G17: https://beautymatter.com/articles/pinterest-predicts-2026 | H17: 2026 | I17: unverified: qualitative, no percentage seen | J17: other: Who What Wear summer 2026: 'oversized satin bow clips' named as trend, 2026 Golden Globes cited (no number) (https://www.whowhatwear.com/beauty/hair/hair-accessories-trends-summer-2026) | K17: unknown; Cider satin bow clip listing on TikTok Shop https://shop.tiktok.com/us/pdp/bow-satin-hair-clip-by-cider-available-in-3-colors-one-size/1729462576036286551 | L17: unknown | M17: none (generic bow) | N17: none | O17: The pink bow is the single most-pinned motif of the niche; no numeric sold count captured before search budget ran out. | P17: REJECT | Q17: Numeric signal exists but weaker than the 40 kept, or it duplicates a kept product in the same look.
A18: C017 | B18: Satin pillowcase (blush / hot pink, ruffle edge) | C18: beauty-selfcare | D18: The Pink Bedroom / Beauty Sleep list | E18: Hot pink satin pillowcase 2/4-pack and blush ruffle set listings live; sold counts not in snippet | F18: TikTok Shop | G18: https://shop.tiktok.com/us/pdp/hot-pink-satin-silk-pillowcases-cooling-envelope-closure/1729502446753716118 | H18: 2026-09 | I18: unverified: no sold count in snippet | K18: unknown | L18: unknown | M18: none | N18: none | O18: Blush ruffle satin pillowcases are the bed-styling pin that pairs with the bonnet and sleep mask. | P18: REJECT | Q18: No numeric signal found (listings exist, counts not visible in snippets).
A19: C018 | B19: Padded / preppy headband (pink, bow or pearl) | C19: beauty-selfcare | D19: The Girly Professional Hair Accessories list | E19: 2026 coverage names 'preppy headbands' as of-the-moment (no number) | F19: Pinterest Predicts | G19: https://beautymatter.com/articles/pinterest-predicts-2026 | H19: 2026 | I19: unverified: qualitative | K19: unknown; multiple pink padded headband listings on TikTok Shop e.g. https://shop.tiktok.com/us/pdp/preppy-pink-padded-headband-with-white-bows-sparkling-gems/1731919925721862765 | L19: unknown | M19: none | N19: none | O19: The pearl-trim pink padded headband is the 'law school' hair accessory. | P19: REJECT | Q19: No numeric signal found (listings exist, counts not visible in snippets).
A20: C019 | B20: Microfiber hair towel wrap (pink) | C20: beauty-selfcare | D20: The Everything Shower list | E20: NO SIGNAL | K20: unknown; TikTok Shop listings e.g. https://shop.tiktok.com/us/pdp/microfiber-hair-towel-wrap-by-formul-a-anti-frizz-super-absorbent-fast-drying/1731938102315487689 | L20: unknown | M20: none | N20: none | O20: Pink towel wrap plus spa headband is the post-shower pin. | P20: REJECT | Q20: No numeric signal found (listings exist, counts not visible in snippets).
A21: C020 | B21: Reusable satin-lined shower cap (pink) | C21: beauty-selfcare | D21: The Everything Shower list | E21: NO SIGNAL | K21: unknown; listing https://shop.tiktok.com/us/pdp/pink-shower-cap-reusable-high-quality-triple-layer-13-inch-diameter-perfect-for-long-hair-dreadlocks/1731429933936120751 | L21: unknown | M21: none (avoid Kitsch branded) | N21: none | O21: Bundles naturally with the bonnet and heatless rod set. | P21: REJECT | Q21: No numeric signal found (listings exist, counts not visible in snippets).
A22: C021 | B22: Satin scrunchie set (pink, oversized) | C22: beauty-selfcare | D22: The Girly Professional Hair Accessories list | E22: NO SIGNAL | K22: unknown; 60-pack listing https://shop.tiktok.com/us/pdp/satin-scrunchies-60-pack-by-silk-elegance-soft-hair-accessories-for-all/1729628567057961975 | L22: unknown | M22: none | N22: none | O22: Low-ticket add-on for the heatless / bonnet bundle. | P22: REJECT | Q22: No numeric signal found (listings exist, counts not visible in snippets).
A23: C022 | B23: Travel jewelry case (pink, small zip) | C23: beauty-selfcare | D23: The Pink Weekend Trip / Bridesmaid Gifting list | E23: NO SIGNAL | K23: unknown; 8-pc bridesmaid pink set listing https://shop.tiktok.com/us/pdp/acrylic-jewelry-box-by-unbranded-clear-organizer-with-15-zipper-bags/1730743806890972120 | L23: unknown | M23: none | N23: none | O23: Fits the travel flat lay with the vanity bag. | P23: REJECT | Q23: No numeric signal found (listings exist, counts not visible in snippets).
A24: C023 | B24: Hanging toiletry bag (pink) | C24: beauty-selfcare | D24: The Pink Weekend Trip list | E24: Keyword page 'western makeup bags pink' shows card with 10 sold at $32.43 (was $60.05, -46%) | F24: TikTok Shop | G24: https://shop.tiktok.com/us/k/western-makeup-bags-pink | H24: 2026-09 (search snippet) | I24: seen in snippet (weak) | K24: TikTok Shop $32.43 (snippet) | L24: unknown | M24: none | N24: none | O24: Secondary to the vanity bag; weak signal. | P24: REJECT | Q24: No numeric signal found (listings exist, counts not visible in snippets).
A25: C024 | B25: Bath caddy tray | C25: beauty-selfcare | D25: The Pink Everything Shower / Bath list | E25: Keyword page 'hygiene caddy' shows card with 1 sold at $8.16 | F25: TikTok Shop | G25: https://shop.tiktok.com/us/k/hygiene-caddy | H25: 2026-09 (search snippet) | I25: seen in snippet (negligible) | K25: unknown | L25: unknown | M25: none | N25: none | O25: Bath-tray pin format is strong but no sales number captured. | P25: REJECT | Q25: No numeric signal found (listings exist, counts not visible in snippets).
A26: C025 | B26: Nail care kit without glue (files, buffers, cuticle tools, pink case) | C26: beauty-selfcare | D26: The Pink Vanity / At-Home Manicure list | E26: NO SIGNAL | K26: unknown | L26: unknown | M26: none (avoid branded gel kits with UV lamps: battery/electronics) | N26: none if tools only | O26: Fits the manicure-Sunday pin; no numbers found before budget ran out. | P26: REJECT | Q26: No numeric signal found (listings exist, counts not visible in snippets).
A27: C026 | B27: Pink calming donut / raised dog bed | C27: dog | D27: Pink Home, Dorm and Car Finds - the pink dog corner | E27: Amazon search 'pink raised dog bed': top results show up to 5K+ bought in past month | F27: Amazon Best Sellers | G27: https://www.amazon.com/pink-raised-dog-bed/s?k=pink+raised+dog+bed | H27: 2026-09-27 | I27: seen in snippet (search-tool summary of Amazon results page; exact ASIN not shown) | J27: Amazon Best Sellers: Amazon search 'pink calming dog bed': popular options show 2K+ bought in past month (https://www.amazon.com/pink-calming-dog-bed/s?k=pink+calming+dog+bed) | Amazon Best Sellers: Amazon search 'pink puppy bed': some products 3K+ bought in past month (https://www.amazon.com/pink-puppy-bed/s?k=pink+puppy+bed) | Amazon Best Sellers: 'Non-Slip Bottom Egg-Crate Memory Foam Big Dog Couch Bed, Dusty Pink, 44 inch' 500+ bought in past month (https://www.amazon.com/dusty-pink-dog-bed/s?k=dusty+pink+dog+bed) | K27: unknown (Amazon price not shown in snippets) | L27: unknown | M27: none | N27: none | O27: A blush dog bed that matches the pink sofa is the flat-lay hero of every 'pink dog mom home' board. | P27: REJECT | Q27: Bulky or heavy: inbound shipping pushes the price out of the Pink Finds band.
A28: C027 | B28: Blush pink packing cubes set (6 to 8 pc) | C28: gifting | D28: Pink travel set / girls-trip packing list | E28: Amazon search 'pink packing cubes': products show from 50+ up to 4K+ bought in past month | F28: Amazon Best Sellers | G28: https://www.amazon.com/pink-packing-cubes/s?k=pink+packing+cubes | H28: 2026-09-27 | I28: seen in snippet (search-tool summary of Amazon results page; which listing carries 4K+ not shown) | J28: other: risingtrends/Glimpse jewelry-trends roundup: travel accessories saw an overall 16% sales increase in the first two months of 2026 (https://www.risingtrends.co/trends/jewelry-trends-2026) | K28: unknown; reference listing BAGAIL 8-set Blush Pink https://www.amazon.com/BAGAIL-Packing-Lightweight-Organizers-Toiletry/dp/B08S38PLQG (price not in snippet) | L28: unknown | M28: none (avoid BAGAIL/BEIS branding) | N28: none | O28: Colour-coordinated pink cubes inside an open suitcase is a classic 'pack with me' pin. | P28: BANK Q13
A29: C028 | B29: Pink velvet jewelry box with lock | C29: gifting | D29: Pink vanity / gifts for her under $40 | E29: Amazon search 'pink jewelry box': 100+ bought in past month; 'pink jewelry gift box': 200+ bought in past month; 'pink jewelry organizer': 50+ bought in past month | F29: Amazon Best Sellers | G29: https://www.amazon.com/pink-jewelry-box/s?k=pink+jewelry+box | H29: 2026-09-27 | I29: seen in snippet (search-tool summary of Amazon results pages) | J29: Amazon Best Sellers: QBestry pink velvet jewelry box with lock (B09SFQ2VGR) 50+ bought in past month (https://www.amazon.com/Organizer-QBestry-Necklace-Bracelets-Earrings/dp/B09SFQ2VGR) | TikTok Shop: TikTok Shop 'hot-pink-jewelry-box' page: items priced $9.99 to $89.99, several showing Sold status with 'thousands of units sold' (https://www.tiktok.com/shop/product/hot-pink-jewelry-box) | K29: $9.99 to $89.99 on TikTok Shop hot-pink jewelry box page (search summary) | L29: unknown | M29: none | N29: none | O29: A blush velvet box open on a marble vanity is the definitive 'gift for her' pin. | P29: BANK Q12
A30: C029 | B30: Pink travel jewelry case (small zip organizer) | C30: gifting | D30: Pink travel set / carry-on essentials | E30: Travel-jewelry products 'soared' in first two months of 2026; travel accessories +16% sales overall | F30: other | G30: https://www.risingtrends.co/trends/jewelry-trends-2026 | H30: 2026 (Jan-Feb) | I30: unverified: figure appeared in search summary; exact page not confirmed | J30: TikTok Shop: Travel jewelry organizer and 'travel jewelry boxes bulk' keyword pages exist on TikTok Shop US (no sold count captured) (https://www.tiktok.com/shop/product/jewelry-travel-organizer) | K30: unknown | L30: unknown | M30: none (avoid BAGSMART branding) | N30: none | O30: Fits the pink packing-cube flat lay; bundles naturally with luggage tag and passport cover. | P30: REJECT | Q30: Numeric signal exists but weaker than the 40 kept, or it duplicates a kept product in the same look.
A31: C030 | B31: Pink paper heart garland (6 ft) | C31: seasonal-valentines | D31: Pink Valentine's mantel / Galentine's table | E31: Etsy listing 'Red & Pink Heart Garland, 6ft strand' (anyoccasionbanners) has 622 favorites | F31: Etsy | G31: https://www.etsy.com/listing/118450280/red-pink-heart-garland-valentines-day | H31: 2026-09-27 | I31: seen in snippet | J31: Etsy: Etsy listing 'Cupid and Heart Garland' (same shop) 125 favorites (https://www.etsy.com/listing/260078255/cupid-and-heart-garland-valentines-day) | Pinterest Trends: Pinterest data: 'Valentine's decor' searches doubled (Forbes, Valentine's 2026 coverage) (https://www.forbes.com/sites/katehardcastle/2026/02/13/valentines-2026-how-galentines-and-friendship-spending-are-expanding-the-business-of-love/) | K31: unknown (Etsy price not in snippet) | L31: unknown | M31: none | N31: none | O31: Cheapest way to make a mantel or desk read 'pink Valentine's' in one pin. | P31: REJECT | Q31: Numeric signal exists but weaker than the 40 kept, or it duplicates a kept product in the same look.
A32: C031 | B32: Galentine's party kit (pink plates, napkins, banner, straws) | C32: seasonal-valentines | D32: Galentine's brunch table, all pink | E32: Pinterest data indicates a 50% rise in 'Galentine's aesthetic' searches | F32: Pinterest Trends | G32: https://www.forbes.com/sites/katehardcastle/2026/02/13/valentines-2026-how-galentines-and-friendship-spending-are-expanding-the-business-of-love/ | H32: 2026-02-13 | I32: seen in snippet | J32: other: 'Galentine's Day alone has surpassed 8.6 million searches, rising by 207%' (https://nationaltoday.com/us/ca/los-angeles/news/2026/02/13/galentines-and-friendship-spending-expand-the-modern-relationship-economy/) | other: Pinterest board '740 Best Galentine's Day Party Ideas in 2026' (prettycollected) holds 740 pins (https://www.pinterest.com/prettycollected/galentines-day-party-ideas/) | K32: unknown | L32: unknown | M32: none (keep text generic, no brand fonts) | N32: none | O32: Galentine's is the fastest-growing February occasion and it is pink by default. | P32: REJECT | Q32: Numeric signal exists but weaker than the 40 kept, or it duplicates a kept product in the same look.
A33: C032 | B33: Pink heart-shaped decor: heart pillow and heart-shaped tray | C33: seasonal-valentines | D33: Pink Valentine's living room / coffee table | E33: 'Valentine's decor' searches doubled on Pinterest (Forbes, Feb 2026) | F33: Pinterest Trends | G33: https://www.forbes.com/sites/katehardcastle/2026/02/13/valentines-2026-how-galentines-and-friendship-spending-are-expanding-the-business-of-love/ | H33: 2026-02-13 | I33: seen in snippet (category-level only; no product-level count found) | K33: unknown | L33: unknown | M33: none | N33: none | O33: Heart pillow on a cream sofa is the lowest-effort Valentine's room refresh. | P33: REJECT | Q33: Numeric signal exists but weaker than the 40 kept, or it duplicates a kept product in the same look.
A34: C033 | B34: Pink bow party decor kit (bow garland, bow cake topper, bow napkins) | C34: gifting | D34: Pink bow party / bow-themed gifts | E34: Pinterest board 'Pink Bow Grad Party ideas in 2026' holds 200 pins; Pinterest has dedicated 'Pink Bow Party' and 'Bow Party Decor' ideas hubs | F34: other | G34: https://www.pinterest.com/ideas/pink-bow-party/955183510608/ | H34: 2026 | I34: seen in snippet (board pin count, weak; no Pinterest Trends percentage captured) | J34: Pinterest Trends: 'Galentine's aesthetic' +50% (bow-themed Galentine's party pins sit inside this trend) (https://www.forbes.com/sites/katehardcastle/2026/02/13/valentines-2026-how-galentines-and-friendship-spending-are-expanding-the-business-of-love/) | K34: unknown | L34: unknown | M34: none (generic bows only) | N34: none | O34: Bows are the signature motif of the pink-girly aesthetic; a bow garland photographs well on any table. | P34: BANK Q07
A35: C034 | B35: Pink ruffle dog bandana with matching bow | C35: dog | D35: Girly dog accessories / dog mom gift list | E35: Etsy listing 'Girly Pink Striped Ruffle Bandana' carries the Bestseller badge ('high sales volume over the past 6 months'); priced EUR 27.41, EUR 31.06 with matching bow | F35: Etsy | G35: https://www.etsy.com/listing/1817731525/custom-embroidered-dog-bandana-girly-dog | H35: 2026-09-27 | I35: seen in snippet (badge, no exact sales count) | J35: Etsy: Etsy 'pink dog bow' market page: 1,000+ unique items listed, prices under GBP 20 to over GBP 100 (https://www.etsy.com/uk/market/pink_dog_bow) | K35: EUR 27.41 bandana / EUR 31.06 with bow (Etsy listing 1817731525) | L35: unknown | M35: none | N35: none | O35: Matching pink bow on the dog is the 'dog mom' pin; low cost, high save rate. | P35: REJECT | Q35: Numeric signal exists but weaker than the 40 kept, or it duplicates a kept product in the same look.
A36: C035 | B36: Pink bow-stem champagne flutes, set of 4 | C36: seasonal-nye | D36: Pink NYE bar cart / Galentine's toast | E36: TikTok Shop champagne-flute keyword page shows per-listing counts of 7, 3, 8 and 56 sold, prices $31.95 to $105.99 | F36: TikTok Shop | G36: https://shop.tiktok.com/us/k/swarovski-champagne-flutes | H36: 2026-09-27 | I36: seen in snippet (keyword page is branded 'swarovski'; counts are for adjacent listings, not the pink bow set) | J36: other: eBay listing 'Pink Bow Gem Champagne Flutes, TikTok Viral Set of 4' describes the set as TikTok-viral limited edition (https://www.ebay.com/itm/276803467251) | K36: unknown for the pink bow set; flutes on TikTok Shop page listed $31.95 to $105.99 | L36: unknown | M36: none (do not source Swarovski-branded items) | N36: none | O36: Bow-stem flutes with pink bubbly is the NYE-to-Valentine's crossover pin. | P36: BANK Q15
A37: C036 | B37: Pink plastic champagne flutes 5.5 oz, non-skid base (party pack) | C37: seasonal-nye | D37: Pink NYE party table | E37: NO SIGNAL | K37: unknown (Amazon listing seen via Movers & Shakers Home & Kitchen search, no rank or count in snippet) | L37: unknown | M37: none | N37: none | O37: Disposable-but-pretty flutes for a pink NYE table. | P37: REJECT | Q37: No numeric signal found (listings exist, counts not visible in snippets).
A38: C037 | B38: Pink bow dog harness, collar and leash set | C38: dog | D38: Girly dog accessories | E38: NO SIGNAL | K38: unknown; Amazon references Didog bow harness set B0C3RVZVND and pink bow-tie harness set B0C48YPPD9 (no counts in snippets) | L38: unknown | M38: none | N38: none | O38: The matching pink harness set is the most-saved dog mom accessory; needs a sales count. | P38: REJECT | Q38: No numeric signal found (listings exist, counts not visible in snippets).
A39: C038 | B39: Pink poop bag holder (velvet / strawberry / PU leather) | C39: dog | D39: Girly dog walk kit | E39: NO SIGNAL | K39: unknown; Amazon listings B0FPFRCT9R (strawberry pink), B0DRW54512 (pink), ARING PET velvet pink store page, no counts in snippets | L39: unknown | M39: none | N39: none | O39: Small pink add-on that completes the leash flat lay. | P39: REJECT | Q39: No numeric signal found (listings exist, counts not visible in snippets).
A40: C039 | B40: Pink pet carrier bag / bubble-window backpack | C40: dog | D40: Pink travel set with the dog | E40: NO SIGNAL | K40: unknown | L40: unknown | M40: none | N40: none | O40: Pink carrier plus pink luggage is the girls-trip-with-dog pin. | P40: REJECT | Q40: No numeric signal found (listings exist, counts not visible in snippets).
A41: C040 | B41: Pink insulated wine tumbler 12 oz with lid | C41: gifting | D41: Pink gifts for her / wine night | E41: NO SIGNAL | K41: unknown; TikTok Shop keyword pages exist (pink tumbler, reduce wine tumbler set) but no counts seen | L41: unknown | M41: none (avoid Stanley/Owala branding) | N41: none | O41: Pink stemless tumbler is a staple gift-guide item. | P41: REJECT | Q41: No numeric signal found (listings exist, counts not visible in snippets).
A42: C041 | B42: Pink robe + slippers + headband spa gift set (no cosmetics) | C42: gifting | D42: Pink self-care night in | E42: NO SIGNAL | K42: unknown | L42: unknown | M42: none | N42: none | O42: Fuzzy slippers were named a viral TikTok gift in 2026 listicles (no number captured); robe bundle is the giftable version. | P42: REJECT | Q42: No numeric signal found (listings exist, counts not visible in snippets).
A43: C042 | B43: Pink 2027 planner / desk calendar | C43: gifting | D43: The Law School Desk Setup, All Pink | E43: NO SIGNAL | K43: unknown; Etsy pink digital planner 2025-2027 listing 1859177189 exists; TikTok Shop '2027 magnet daily planner' listed as coming soon | L43: unknown | M43: none | N43: none | O43: New-year planner pins spike in December; pink cover is the desk flat-lay anchor. | P43: BANK Q16
A44: C043 | B44: Pink NYE decor: balloon garland, sequin table runner, disco ball ornaments, pink party hats | C44: seasonal-nye | D44: Pink New Year's Eve party decor list | E44: NO SIGNAL | K44: unknown | L44: unknown | M44: none (use generic '2027' only) | N44: none | O44: Trade press says pink is a standout holiday 2026 colour story (Home Accents Today, Gift Shop Magazine) but no number was captured. | P44: REJECT | Q44: No numeric signal found (listings exist, counts not visible in snippets).
A45: C044 | B45: Pink satin pajama set | C45: seasonal-valentines | D45: Galentine's sleepover / Valentine's morning | E45: NO SIGNAL | K45: unknown | L45: unknown | M45: none | N45: none | O45: Matching satin PJs are the Galentine's photo uniform. | P45: REJECT | Q45: Sized apparel: returns run well above the 8% allowance and Tommy Kate cannot wear blazers; kept for the Amazon pipeline, not the store.
A46: C045 | B46: Pink luggage tag + passport holder set | C46: gifting | D46: Pink travel set | E46: NO SIGNAL | K46: unknown; branded reference (BEIS) exists at ~premium price, not for sourcing | L46: unknown | M46: note: do not copy BEIS trade dress | N46: none | O46: Completes the pink packing-cube flat lay. | P46: REJECT | Q46: No numeric signal found (listings exist, counts not visible in snippets).
A47: C046 | B47: Pink stationery gift set, pink 1000-piece puzzle / game-night set, dog mom gift box | C47: gifting | D47: Pink gifts for her / dog mom gifts | E47: NO SIGNAL | K47: unknown | L47: unknown | M47: none | N47: none | O47: Not searched: WebSearch budget was exhausted before these subcategories were reached. | P47: REJECT | Q47: No numeric signal found before the search budget ran out (no signal, no product).
A48: C047 | B48: Fluffy / plush pink steering wheel cover (universal 15in) | C48: car | D48: Pink Home, Dorm and Car Finds - the pink car interior | E48: keyword page 'fluffy pink steering wheel cover': 57.0K total sold across verified shops; top listing 236 sold, limited-time-deal listing 6.6K sold | F48: TikTok Shop | G48: https://shop.tiktok.com/us/k/fluffy-pink-steering-wheel-cover | H48: live page, seen 2026-09-27 | I48: seen in search snippet (aggregate keyword-page figure, per-listing split not fully visible) | J48: TikTok Shop: keyword page 'steering wheel cover pink': 58.0K total sold from verified shops (19.2K followers) (https://shop.tiktok.com/us/k/steering-wheel-cover-pink) | TikTok Shop: keyword page 'fuzzy steering wheel cover pink': 236 sold, discounted (https://shop.tiktok.com/us/k/fuzzy-steering-wheel-cover-pink) | K48: unknown exact; TikTok Shop listings shown as discounted deals (price not visible in snippet) | L48: unknown (AliExpress listings exist but price not in snippet) | M48: none if plain/fluffy; avoid Kuromi/Hello Kitty/Barbie variants that dominate the AliExpress wiki pages | N48: none (avoid the 'LED steering cover' variant) | O48: The single most saved 'pink car' item: instant pink-car transformation for under $20, photographs perfectly from the driver seat. | P48: BANK E08
A49: C048 | B49: Pink cow-print steering wheel cover | C49: car | D49: Pink Home, Dorm and Car Finds - pink car interior (western-girly variant) | E49: keyword page 'pink cow print steering wheel cover': 251 sold | F49: TikTok Shop | G49: https://shop.tiktok.com/us/k/pink-cow-print-steering-wheel-cover | H49: live page, seen 2026-09-27 | I49: seen in search snippet | K49: unknown | L49: unknown | M49: none (generic print) | N49: none | O49: Pattern variant of the winning product; pins into 'pink western' and 'coquette cowgirl' boards. | P49: REJECT | Q49: Numeric signal exists but weaker than the 40 kept, or it duplicates a kept product in the same look.
A50: C049 | B50: Pink PU-leather full-set car seat covers (5 or 7 seat, airbag compatible) | C50: car | D50: Pink Home, Dorm and Car Finds - full pink car interior makeover | E50: 7-seater pink PU leather seat cover set: 35 sold, $51.14 (45% off $93.00), free shipping | F50: TikTok Shop | G50: https://shop.tiktok.com/us/pdp/autoyouth-7-seat-pink-pu-leather-car-seat-covers-universal-fit/1729495851509257503 | H50: live page, seen 2026-09-27 | I50: seen in search snippet | K50: $51-$93 on TikTok Shop (7-seat set); 5-seat pink PU set also listed https://shop.tiktok.com/us/pdp/car-seat-covers-waterproof-pu-leather-for-women-pink-universal-fit/1729616282892341296 | L50: unknown | M50: none for generic; do not use seller brand names | N50: none | O50: High-ticket, high-visual 'before/after' pink car pin; buyer is a woman upgrading a used car interior. | P50: REJECT | Q50: Bulky or heavy: inbound shipping pushes the price out of the Pink Finds band.
A51: C050 | B51: Bling rhinestone pink car seat covers (full set) | C51: car | D51: Pink Home, Dorm and Car Finds - glam / bling pink car | E51: keyword page 'car accessories pink and fluffy': 79 sold (top listing) - related bling searches | F51: TikTok Shop | G51: https://shop.tiktok.com/us/k/car-accessories-pink-and-fluffy | H51: live page, seen 2026-09-27 | I51: seen in search snippet (keyword-page top listing, not the exact seat cover) | K51: unknown (listing https://shop.tiktok.com/us/pdp/car-seat-covers-by-car-pass-pink-rhinestone-faux-leather-universal-fit/1729487132212695548) | L51: unknown | M51: none | N51: none | O51: Sparkle reads on camera; pairs with the bling coasters and steering cover for a 'set' pin. | P51: REJECT | Q51: Bulky or heavy: inbound shipping pushes the price out of the Pink Finds band.
A52: C051 | B52: 43-piece fuzzy pink car interior set (seat covers + steering + belt + handbrake covers) | C52: car | D52: Pink Home, Dorm and Car Finds - one-click pink car interior bundle | E52: 43 pcs fuzzy pink set listed at $69.13 (33% off $103.18), seller AutoChic Interior, free shipping (sold count not visible in snippet) | F52: TikTok Shop | G52: https://shop.tiktok.com/us/pdp/43-pcs-fuzzy-car-seat-cover-set-for-women-pink-accessories-full-coverage/1732263138563953554 | H52: live page, seen 2026-09-27 | I52: price seen in snippet; unverified: sold count not shown | K52: $69.13 (TikTok Shop, discounted from $103.18) | L52: unknown | M52: none | N52: none | O52: Bundle = one pin, one purchase; 'everything you need for a pink car' listicle format. | P52: REJECT | Q52: Bulky or heavy: inbound shipping pushes the price out of the Pink Finds band.
A53: C052 | B53: Pink vacuum / magnetic suction car phone holder (no electronics) | C53: car | D53: Pink Home, Dorm and Car Finds - pink dashboard essentials | E53: vacuum magnetic suction phone holder, pink option: 27 sold, $10.99, seller AKnmenm | F53: TikTok Shop | G53: https://shop.tiktok.com/us/pdp/vacuum-magnetic-suction-phone-holder-upgraded-stability-dual-sided-magnetic-hands-free-convenience/1732202859492512145 | H53: live page, seen 2026-09-27 | I53: seen in search snippet | K53: $10.99 (TikTok Shop) | L53: unknown | M53: none | N53: none (passive suction/magnet; avoid the 'flowing sand aromatherapy' version which showed 0 sold / out of stock) | O53: Functional pink dashboard piece; fits the 'pink car essentials' checklist pin. | P53: BANK E12
A54: C053 | B54: Pink floral quilted car storage basket / back-seat organizer | C54: car | D54: Pink Home, Dorm and Car Finds - pink car organisation | E54: car storage basket organizer (pink option): 2 sold, $23.86, seller StarHHK Daily | F54: TikTok Shop | G54: https://shop.tiktok.com/us/pdp/car-storage-basket-organizer-multifunctional-durable/1731987134742434516 | H54: live page, seen 2026-09-27 | I54: seen in search snippet (weak: 2 sold) | J54: TikTok Shop: floral quilted foldable basket (car trunk / laundry, pink option): 20.0K sold, 54% off (https://shop.tiktok.com/us/pdp/floral-pattern-foldable-laundry-basket-large-capacity-organizer-ideal-for-living-room-bedroom-bathro/1731421365291684567) | K54: $23.86 (TikTok Shop) | L54: AliExpress pink car trunk organizer $21.08 (20 sold) https://www.aliexpress.com/i/3256810032994368.html | M54: none | N54: none | O54: Same quilted-floral basket sells 20K as a laundry basket; the car-use pin is the same product photographed on a back seat. | P54: REJECT | Q54: Numeric signal exists but weaker than the 40 kept, or it duplicates a kept product in the same look.
A55: C054 | B55: Pink car floor mats (polka-dot bow print or bling leather 4-5 pc set) | C55: car | D55: Pink Home, Dorm and Car Finds - pink car interior | E55: 4pcs polka-dot bow car floor mats: 7 sold | F55: TikTok Shop | G55: https://shop.tiktok.com/us/pdp/4pcs-car-floor-mats-set-durable-all-weather-design-polka-dot-style-easy-to-clean-for-sedans-and-suvs/1729495989295027308 | H55: live page, seen 2026-09-27 | I55: seen in search snippet (weak: 7 sold) | K55: unknown; pink bling leather mat set listed https://shop.tiktok.com/us/pdp/pink-bling-diamond-car-mats-set-waterproof-leather-anti-slip/1731263851229385378 | L55: unknown | M55: none (avoid 'pink weathertech' keyword - trademark) | N55: none | O55: Completes the floor-to-wheel pink car set; bow print ties to the bow trend. | P55: REJECT | Q55: Numeric signal exists but weaker than the 40 kept, or it duplicates a kept product in the same look.
A56: C055 | B56: Pink snow brush + ice scraper (car winter kit) | C56: car | D56: Pink Home, Dorm and Car Finds - pink car winter / emergency kit (Q4 seasonal) | E56: Autovir 27in snow brush & ice scraper 3-pack (pink option) appears on Movers & Shakers Automotive (rank and % gain not visible in snippet) | F56: Amazon Movers & Shakers | G56: https://www.amazon.com/gp/movers-and-shakers/automotive | H56: live page, seen 2026-09-27 | I56: unverified: rank/percentage not shown in snippet; presence on the list only | K56: unknown; Walmart carries 'Mallory 994 Pink Ice Scraper 10in' https://www.walmart.com/ip/32593761 | L56: unknown | M56: none if unbranded | N56: none | O56: Seasonal Oct-Jan pin: 'pink car winter essentials' checklist; low price, giftable. | P56: REJECT | Q56: Numeric signal exists but weaker than the 40 kept, or it duplicates a kept product in the same look.
A57: C056 | B57: Wavy / wave-shaped wall mirror (no lights) | C57: home-cozy | D57: Pink Home, Dorm and Car Finds - pink dorm / bedroom wall | E57: keyword page 'shop wavy mirror': top listing 964 sold, $33.77 limited-time deal | F57: TikTok Shop | G57: https://shop.tiktok.com/us/k/shop-wavy-mirror | H57: live page, seen 2026-09-27 | I57: seen in search snippet | J57: TikTok Shop: keyword page 'wave mirrors': listing 367 sold, $21.39 (https://shop.tiktok.com/us/k/wave-mirrors) | other: The Range 'Top Trending Mirrors for 2026' lists wavy designs among trending shapes (no number) (https://www.therange.co.uk/blog/home-soft-furnishings/top-trending-mirrors/) | K57: $21-$34 on TikTok Shop (small/desk sizes); pink wavy desk mirror 6.69in listed https://shop.tiktok.com/us/pdp/wavy-design-compact-pink-color-portable-folding-desk-mirror/1731831737431134300 | L57: unknown | M57: none | N57: none (exclude the 'wavy light-up mirror' variant, 254 sold, which has LEDs) | O57: The signature shape of the pink dorm/bedroom aesthetic; a pink-framed wavy mirror is a top-of-board image. | P57: REJECT | Q57: Bulky or heavy: inbound shipping pushes the price out of the Pink Finds band.
A58: C057 | B58: Pink laundry basket / hamper (large woven or on wheels) | C58: home-cozy | D58: Pink Home, Dorm and Car Finds - pink dorm laundry corner | E58: keyword page 'target pink basket large': 137 sold, $22.40 (34% off $34.00) | F58: TikTok Shop | G58: https://shop.tiktok.com/us/k/target-pink-basket-large | H58: live page, seen 2026-09-27 | I58: seen in search snippet | J58: TikTok Shop: keyword page 'pink laundry hamper with wheels': 20 sold, $31.13 (35% off $47.89) (https://shop.tiktok.com/us/k/pink-laundry-hamper-with-wheels) | TikTok Shop: floral quilted foldable laundry basket (pink option): 20.0K sold, 54% off (https://shop.tiktok.com/us/pdp/floral-pattern-foldable-laundry-basket-large-capacity-organizer-ideal-for-living-room-bedroom-bathro/1731421365291684567) | K58: $22-$31 (TikTok Shop) | L58: unknown | M58: none (do not use 'Target' in copy; the keyword is a shopper search term) | N58: none | O58: Dorm-and-apartment staple; a 20K-sold quilted floral basket proves demand for soft pink storage. | P58: REJECT | Q58: Bulky or heavy: inbound shipping pushes the price out of the Pink Finds band.
A59: C058 | B59: Coffee syrup pump dispensers (pink, fits 750ml bottles) | C59: home-cozy | D59: Pink Home, Dorm and Car Finds - the pink coffee bar | E59: 4-pack coffee syrup pump dispenser (fits 25.4oz/750ml bottles): 775 sold, $6.99, 4.6 rating | F59: TikTok Shop | G59: https://shop.tiktok.com/us/pdp/coffee-syrup-pump-dispenser-by-syruvia-for-25-4-oz-bottles-4-pack/1730656466901963654 | H59: live page, seen 2026-09-27 | I59: seen in search snippet | J59: TikTok Shop: 10-count pink plastic syrup pumps 750ml-1L listed (sold count not in snippet) (https://shop.tiktok.com/us/pdp/coffee-syrup-pump-10-count-pink-plastic-easy-dose-dispensing/1731302624438359002) | K59: $6.99 for 4 (TikTok Shop) | L59: unknown | M59: none (do not mention Torani/Starbucks/Monin compatibility by brand in pins) | N59: none (food contact plastic; state BPA-free) | O59: The 'home coffee bar' pin format is huge; pink pumps are the cheapest visible upgrade. | P59: REJECT | Q59: Numeric signal exists but weaker than the 40 kept, or it duplicates a kept product in the same look.
A60: C059 | B60: Bow glass cup 16oz with bamboo lid and glass straw (pink, set of 2) | C60: home-cozy | D60: Pink Home, Dorm and Car Finds - the pink coffee bar / iced coffee | E60: keyword page 'bow cup with straw': 443 sold, flash sale $12.47 (-58% from $29.49) | F60: TikTok Shop | G60: https://shop.tiktok.com/us/k/bow-cup-with-straw | H60: live page, seen 2026-09-27 | I60: seen in search snippet | J60: TikTok Shop: pink & gold butterfly 16oz glass cup with bling lid + straw: 6 sold, $20.00 (https://shop.tiktok.com/us/pdp/glass-cup-16oz-pink-gold-butterfly-with-bling-lid-straw/1729385926993875734) | K60: $12.47-$22 (TikTok Shop); coquette bow glass cup gift set (bamboo lid, glass + steel straw, brush, gift box) https://shop.tiktok.com/us/pdp/coquette-cute-pink-bow-glass-cups-with-lids-straws-16oz/1732209478379343983 | L60: unknown | M60: none (avoid 'Starbucks cup' phrasing) | N60: none | O60: Bow + iced coffee + pink = the exact coquette flat-lay; gift-box version doubles as a gifting pin. | P60: REJECT | Q60: Numeric signal exists but weaker than the 40 kept, or it duplicates a kept product in the same look.
A61: C060 | B61: Pink reusable plastic party / iced-coffee cups (16oz pack) | C61: home-cozy | D61: Pink Home, Dorm and Car Finds - pink hosting / coffee bar | E61: keyword page 'pink solo cups': 1.9K sold, $25.99 (-26% from $34.99) | F61: TikTok Shop | G61: https://shop.tiktok.com/us/k/pink-solo-cups | H61: live page, seen 2026-09-27 | I61: seen in search snippet | J61: TikTok Shop: 50-pack pink clear plastic cups with lids and straws 12oz listed (sold count not in snippet) (https://shop.tiktok.com/us/pdp/50-pack-leak-proof-pink-clear-plastic-cups-with-lids-straws/1732283083130900570) | K61: $25.99 per pack (TikTok Shop) | L61: unknown | M61: note: 'Solo' is a trademark - sell as 'pink party cups', never 'pink Solo cups' | N61: none | O61: Pink hosting/bachelorette/girls-night pin; consumable so repeat purchase. | P61: BANK Q05
A62: C061 | B62: Pink stick-on bathroom caddy set (5-pack, stainless, toothbrush + soap holder) | C62: home-cozy | D62: Pink Home, Dorm and Car Finds - pink bathroom / dorm shower | E62: pink bathroom accessories keyword results: listing with 85 sold at $15.80 | F62: TikTok Shop | G62: https://shop.tiktok.com/us/k/pink-soap-dispenser-set | H62: live page, seen 2026-09-27 | I62: seen in search snippet (85 sold figure appears in the results set; exact listing attribution not certain) | K62: $15.80 (TikTok Shop) | L62: unknown | M62: none | N62: none | O62: No-drill pink bathroom refresh for renters and dorms; sits in 'pink bathroom' boards. | P62: REJECT | Q62: Numeric signal exists but weaker than the 40 kept, or it duplicates a kept product in the same look.
A63: C062 | B63: Pink wearable / hooded fleece blanket | C63: home-cozy | D63: Pink Home, Dorm and Car Finds - cozy pink living room | E63: keyword page 'pink snuggie blanket': 167 sold, $4.65 | F63: TikTok Shop | G63: https://shop.tiktok.com/us/k/pink-snuggie-blanket | H63: live page, seen 2026-09-27 | I63: seen in search snippet | K63: $4.65 (TikTok Shop, deal price) | L63: unknown | M63: note: 'Snuggie' is a trademark - list as 'wearable blanket' | N63: none (exclude the pink electric blanket, 75 sold, which is a heated electrical item) | O63: Fall/winter cozy-girl pin; low price point drives impulse saves. | P63: BANK E24
A64: C063 | B64: Pink bow bedding / duvet set | C64: home-cozy | D64: Pink Home, Dorm and Car Finds - coquette pink bedroom | E64: keyword page 'bedding set pink bow': 8 sold, $13.61-$52.99 | F64: TikTok Shop | G64: https://shop.tiktok.com/us/k/bedding-set-pink-bow | H64: live page, seen 2026-09-27 | I64: seen in search snippet (weak: 8 sold) | K64: $13.61-$52.99 (TikTok Shop) | L64: unknown | M64: none | N64: none | O64: Bow print bedding is the hero image of every coquette dorm board. | P64: REJECT | Q64: Bulky or heavy: inbound shipping pushes the price out of the Pink Finds band.
A65: C064 | B65: Small fluffy pink bedroom / bedside rug | C65: home-cozy | D65: Pink Home, Dorm and Car Finds - pink dorm floor | E65: keyword page 'small carpet for bedroom pink': 15 sold, $15.97 (from $25.34), limited-time deal | F65: TikTok Shop | G65: https://shop.tiktok.com/us/k/small-carpet-for-bedroom-pink | H65: live page, seen 2026-09-27 | I65: seen in search snippet | J65: AliExpress: VIKAMA pink round fluffy rug: 8 sold (https://www.aliexpress.com/i/3256811355276707.html) | K65: $15.97 (TikTok Shop) | L65: unknown (AliExpress item 3256811355276707) | M65: none | N65: none | O65: Cheap floor colour for renters; checkerboard pink version had no numeric signal (see no-signal). | P65: REJECT | Q65: Bulky or heavy: inbound shipping pushes the price out of the Pink Finds band.
A66: C065 | B66: 12-in-1 pink silicone kitchen utensil set | C66: home-cozy | D66: Pink Home, Dorm and Car Finds - pink kitchen | E66: 12-in-1 pink silicone utensil set: 1 sold, $32.21, seller Elite Fly, out of stock | F66: TikTok Shop | G66: https://shop.tiktok.com/us/pdp/12-in-1-pink-silicone-kitchen-utensil-set-food-grade-tools/1732219701916766908 | H66: live page, seen 2026-09-27 | I66: seen in search snippet (very weak: 1 sold) | K66: $32.21 (TikTok Shop) | L66: unknown | M66: none | N66: none (food-grade silicone, state heat rating) | O66: Pink kitchen flat-lay anchor; signal is weak on TikTok Shop, so treat as Amazon/Pinterest-led product. | P66: REJECT | Q66: Numeric signal exists but weaker than the 40 kept, or it duplicates a kept product in the same look.
A67: C066 | B67: Pastel pink wall shelf (dorm / vanity) | C67: home-cozy | D67: Pink Home, Dorm and Car Finds - pink dorm wall | E67: Listicle (Printify / adnabu TikTok trending products 2026) quotes a seller A/B test: pastel pink wall shelf had 40% higher ad engagement among Gen Z vs other colour | F67: other | G67: https://printify.com/blog/tiktok-trending-products/ | H67: 2026 | I67: unverified: secondhand A/B-test figure, original seller not named | K67: unknown | L67: unknown | M67: none | N67: none | O67: Wall shelves are the backdrop of every 'pink desk setup' pin; pink colourway lifts engagement. | P67: REJECT | Q67: Bulky or heavy: inbound shipping pushes the price out of the Pink Finds band.
A68: C067 | B68: Pink car trash can with lid (mini, hooks, leak-proof) | C68: car | D68: Pink Home, Dorm and Car Finds - pink car essentials | E68: NO SIGNAL | K68: unknown (TikTok Shop listing exists: https://shop.tiktok.com/us/pdp/pink-car-trash-can-with-lid-hooks-compact-odor-proof/1731541502944252808) | L68: unknown | M68: none | N68: none | O68: Every 'pink car must-haves' pin includes one; no sold count visible in snippets. | P68: BANK E09
A69: C068 | B69: Bling rhinestone / pink glitter car cup-holder coasters (2-4 pack) | C69: car | D69: Pink Home, Dorm and Car Finds - pink car essentials | E69: keyword page 'hot pink car accesories': top listing 6 sold, $6.60 (from $11.75) - bling coasters appear in related searches | F69: TikTok Shop | G69: https://shop.tiktok.com/us/k/hot-pink-car-accesories | H69: live page, seen 2026-09-27 | I69: seen in search snippet; unverified: not confirmed to be the coaster listing | K69: unknown; TikTok Shop 2-pack bling rhinestone coasters https://shop.tiktok.com/us/pdp/car-cup-coasters-2-pack-by-bling-2-75-rhinestone-anti-slip-design/1730861607420793495; Etsy pink glitter car coasters https://www.etsy.com/listing/1449206434/pink-glitter-car-coasters-pink-car | L69: unknown | M69: none | N69: none | O69: Cheapest bling add-on; ideal bundle item. Numeric signal not clearly attributable. | P69: BANK E10
A70: C069 | B70: Plush pink seat-belt covers (2-pack) | C70: car | D70: Pink Home, Dorm and Car Finds - pink car essentials | E70: NO SIGNAL | K70: unknown (TikTok Shop listing https://shop.tiktok.com/us/pdp/soft-comfortable-plush-car-seatbelt-cover-pink-2-pack/1732037604390703284) | L70: unknown | M70: none (avoid 'jelly cat seat belt covers' keyword - Jellycat trademark) | N70: none | O70: Matches fluffy steering cover; bundle item. | P70: BANK E11
A71: C070 | B71: Pink car tissue box holder (visor / armrest) | C71: car | D71: Pink Home, Dorm and Car Finds - pink car essentials | E71: NO SIGNAL | K71: unknown; a black/red universal holder showed 4 sold https://shop.tiktok.com/us/pdp/universal-car-tissue-box-holder-hanging-paper-dispenser/1732088208749400647 | L71: unknown | M71: none | N71: none | O71: Practical pink car pin; no pink-specific number found. | P71: REJECT | Q71: No numeric signal found (listings exist, counts not visible in snippets).
A72: C071 | B72: Flower / daisy car vent clips (decorative, unscented holder, set of 4) | C72: car | D72: Pink Home, Dorm and Car Finds - pink car essentials | E72: NO SIGNAL | K72: unknown (TikTok Shop listing https://shop.tiktok.com/us/pdp/car-air-freshener-clip-by-cute-flower-alloy-daisy-design-set-of-four/1729451266155254730) | L72: unknown | M72: none | N72: none as decorative clip; liability note: if sold scented, fragrance oil is a chemical product (labelling, allergen, spill on dash) - prefer unscented decorative clip | O72: Tiny, cheap, photographs in the vent close-up shot. | P72: REJECT | Q72: No numeric signal found (listings exist, counts not visible in snippets).
A73: C072 | B73: Pink bow car headrest neck pillows (2-pack) | C73: car | D73: Pink Home, Dorm and Car Finds - pink car interior | E73: NO SIGNAL | K73: unknown (TikTok Shop listing https://shop.tiktok.com/us/pdp/cute-pink-bow-car-headrest-pillow-set-soft-stylish/1732280398831653831) | L73: unknown | M73: none | N73: none | O73: Bow trend crossed with car interior; visible from the rear-seat photo. | P73: REJECT | Q73: No numeric signal found (listings exist, counts not visible in snippets).
A74: C073 | B74: Pink bow throw pillow / bow-shaped cushion | C74: home-cozy | D74: Pink Home, Dorm and Car Finds - coquette pink bedroom | E74: NO SIGNAL | K74: unknown; Etsy coquette bow throw pillow listed Apr 12 2026 https://www.etsy.com/listing/1730755856/coquette-throw-pillow-pink-bows-pink; TikTok Shop pink bow pillow https://shop.tiktok.com/us/pdp/pink-bow-pillow-soft-decorative-cushion-for-bed-sofa/1731402404751643417 | L74: unknown | M74: none | N74: none | O74: Core coquette object; sales counts were not exposed in Etsy/TikTok snippets. | P74: REJECT | Q74: No numeric signal found (listings exist, counts not visible in snippets).
A75: C074 | B75: Pink bow flannel throw blanket (coquette print) | C75: home-cozy | D75: Pink Home, Dorm and Car Finds - cozy pink living room | E75: NO SIGNAL | K75: unknown (TikTok Shop listing https://shop.tiktok.com/us/pdp/pink-bow-christian-throw-blanket-god-says-i-am-coquette-style/1732253460881510477) | L75: unknown | M75: none | N75: none | O75: Print-on-demand friendly (Printify/Printful blanket) so zero inventory; no sold count seen. | P75: REJECT | Q75: No numeric signal found (listings exist, counts not visible in snippets).
A76: C075 | B76: Pink bow and hearts ceramic mug (11/15oz) | C76: home-cozy | D76: Pink Home, Dorm and Car Finds - the pink coffee bar | E76: NO SIGNAL | K76: unknown (TikTok Shop listing https://shop.tiktok.com/us/pdp/pink-bow-heart-design-ceramic-coffee-mug-11oz-15oz-options/1729492075436610648) | L76: unknown | M76: none | N76: none | O76: POD mug = zero stock; pairs with syrup pumps and bow glass cup in one coffee-bar pin. | P76: REJECT | Q76: No numeric signal found (listings exist, counts not visible in snippets).
A77: C076 | B77: Pink bows & hearts soap dispenser / pink glass 16oz soap dispenser | C77: home-cozy | D77: Pink Home, Dorm and Car Finds - pink bathroom | E77: NO SIGNAL | K77: unknown (TikTok Shop listings https://shop.tiktok.com/us/pdp/whimsical-pink-bows-heart-soap-dispenser-cute-bathroom-kitchen/1732144138587050778 and https://shop.tiktok.com/us/pdp/pink-glass-soap-dispenser-with-plastic-pump-16-oz-capacity/1731324930288291902) | L77: unknown | M77: none | N77: none | O77: Sink-side hero of the pink bathroom pin. | P77: REJECT | Q77: No numeric signal found (listings exist, counts not visible in snippets).
A78: C077 | B78: Bow-shaped pink wax melts / pink bow candle | C78: home-cozy | D78: Pink Home, Dorm and Car Finds - cozy pink living room | E78: NO SIGNAL | K78: unknown (TikTok Shop listing https://shop.tiktok.com/us/pdp/pink-bubblegum-scented-bow-shaped-wax-melts-made-with-paraffin-wax-essential-oils/1731485301992428390) | L78: unknown | M78: none | N78: none for flame candle/melts (note: the Etsy 'pink cherry bow candle warmer lamp' is electric - excluded) | O78: Bow-shaped wax is a pure Pinterest object; no sold count found. | P78: REJECT | Q78: No numeric signal found (listings exist, counts not visible in snippets).
A79: C078 | B79: Pink apron + oven mitt set | C79: home-cozy | D79: Pink Home, Dorm and Car Finds - pink kitchen | E79: NO SIGNAL | K79: unknown | L79: unknown | M79: note: the visible top seller is a Paris Hilton branded 'That's HOT' mitt set - do not copy the phrase or name | N79: none | O79: Pink kitchen gifting pin; the only numbered listing is celebrity-branded, so generic demand unproven. | P79: REJECT | Q79: No numeric signal found (listings exist, counts not visible in snippets).
A80: C079 | B80: Pink checkerboard rug | C80: home-cozy | D80: Pink Home, Dorm and Car Finds - pink dorm floor | E80: NO SIGNAL | K80: unknown | L80: unknown | M80: none | N80: none | O80: Requested item; searches surfaced pink rugs and checkered rugs separately but no pink-checkerboard listing with a count. | P80: REJECT | Q80: Bulky or heavy: inbound shipping pushes the price out of the Pink Finds band.
A81: C080 | B81: Pink entryway tray and wall hooks; pink car emergency kit; velvet/boucle pink cushions; pink diffuser | C81: home-cozy | D81: Pink Home, Dorm and Car Finds | E81: NO SIGNAL | K81: unknown | L81: unknown | M81: none | N81: none | O81: Not searched - web search budget was exhausted at 200/200 session calls before these queries ran; lead should re-run with budget raised. | P81: REJECT | Q81: No numeric signal found before the search budget ran out (no signal, no product).
A82: C081 | B82: Pink PU leather desk mat / desk pad (large, waterproof, dual-sided) | C82: workwear-office | D82: The Law School Desk Setup, All Pink | E82: ASINsight 'pink desk pad' report: #1 ASIN B09DV56338 est. 10,000 monthly sales (down 20.0% MoM), #2 B085XRMSTT 6K/month, #3 B0CZDQ1SGG 5K/month; 131 tracked products; $10-$20 price zone = 59% of assortment | F82: Amazon Best Sellers | G82: https://www.asinsight.com/report/US/pink-desk-pad | H82: June 2026 | I82: seen in snippet | J82: TikTok Shop: Keyword page 'desk mats pink leather' shows pink leather desk mat with 174 sold (https://shop.tiktok.com/us/k/desk-mats-pink-leather) | Etsy: Etsy market page lists bestsellers: Scalloped Gingham Desk Mat, Pastel Checkered wavy-edge desk mat, Coquette personalized desk pad (no sales counts in snippet) (https://www.etsy.com/market/pink_desk_mat) | K82: $10-$20 is the dominant Amazon price zone (ASINsight); TikTok Shop pink leather desk mats in the same range | L82: AliExpress felt/PU desk mats from about $0.99-$6 (AliExpress wholesale page https://www.aliexpress.com/w/wholesale-pink-desk-mat.html; felt XL mat 10,000+ sold at $0.99 https://aliexpress.com/item/1005006086188422.html) | M82: none (avoid Barbie/Hello Kitty prints) | N82: none | O82: One flat-lay hero piece that instantly turns any desk photo into the pink law-school aesthetic. | P82: BANK E01
A83: C082 | B83: Pink desk mat + keyboard wrist rest + mouse wrist rest 3-piece set | C83: workwear-office | D83: The Law School Desk Setup, All Pink | E83: Keyword page 'keyboard and mouse wrist pad pink and black' shows listing with 229 sold | F83: TikTok Shop | G83: https://shop.tiktok.com/us/k/keyboard-and-mouse-wrist-pad-pink-and-black | H83: seen 27 Sep 2026 | I83: seen in snippet | J83: Amazon Best Sellers: ASINsight has a dedicated 'pink mouse pad with wrist rest' top-10 sales report for 2026 (numbers not visible in snippet) (https://www.asinsight.com/report/US/pink-mouse-pad-with-wrist-rest) | K83: Amazon: Bloss Pink Desk Mat + Wrist Rest set (B0H25744PZ), Anyshock Light Pink set (B0BXD4MCCK) - prices not in snippet; comparable desk-pad sets sit $10-$20 per ASINsight | L83: unknown | M83: none | N83: none | O83: Ergonomic and matching in one click; the wrist rests make the whole keyboard zone pink for the WFH desk photo. | P83: REJECT | Q83: Numeric signal exists but weaker than the 40 kept, or it duplicates a kept product in the same look.
A84: C083 | B84: Pink acrylic desk organizer / pen cup + tray set | C84: workwear-office | D84: The Law School Desk Setup, All Pink | E84: Amazon search 'pink acrylic desk organizer': listing with 100+ bought in past month at $13.99; 'pink desk organizer set' 200+ bought in past month; 'acrylic desk organizer set' 300+ bought; generic 'acrylic desk organizer' 4K+ bought in past month | F84: Amazon Best Sellers | G84: https://www.amazon.com/pink-acrylic-desk-organizer/s?k=pink+acrylic+desk+organizer | H84: seen 27 Sep 2026 | I84: seen in snippet | J84: TikTok Shop: Keyword page 'office desk accessories pink' shows products ranging 13 to 1.3K sold, ratings 4.5-4.8; 'hot pink desk organizer ideas' products 9 to 658 sold (https://shop.tiktok.com/us/k/office-desk-accessories-pink) | Amazon Best Sellers: ASINsight 'pink desk organizer' 2026 report, #1 brand gianotter (numbers not in snippet) (https://www.asinsight.com/report/US/pink-desk-organizer) | K84: $13.99 on Amazon (snippet); TikTok Shop similar | L84: AliExpress hot pink mesh 7-compartment desk organizer with drawer US$6.79 (https://www.aliexpress.com/item/32824372086.html) | M84: none | N84: none | O84: Acrylic + pink reads 'organised corporate girlie'; a cheap, high-visual-impact restock for any desk tour. | P84: BANK E02
A85: C084 | B85: Pink desk stationery set (stapler, tape dispenser, scissors, clips, staple remover) | C85: workwear-office | D85: The Law School Desk Setup, All Pink | E85: Amazon 'pink office supplies' set (stapler, tape dispenser, scissors, clips, 1000 staples) 500+ bought in past month; UPIHO pink stapler & tape dispenser set (B0B9MCDC74) 200+ bought in past month; WORKPRO pink mini stapler set (B0DBKND2Y5) 300+ bought; Knamoda pink mini stapler 2K+ bought in past month | F85: Amazon Best Sellers | G85: https://www.amazon.com/pink-stapler-tape-dispenser-set/s?k=pink+stapler+and+tape+dispenser+set | H85: seen 27 Sep 2026 | I85: seen in snippet | K85: unknown (Amazon set listings B0B9MCDC74, B0DBKND2Y5; price not in snippet) | L85: unknown (Temu 11-pc pink office supplies set and 9-pc pink set listed; price not in snippet) | M85: none | N85: none | O85: The matching-set instinct: every tool on the desk in the same blush, which is the whole point of the pin. | P85: BANK E03
A86: C085 | B86: Generic pink 40 oz insulated tumbler with handle and straw | C86: workwear-office | D86: The Law School Desk Setup, All Pink / Pink desk essentials | E86: ASINsight 'pink tumbler with straw' report: #1 ASIN B0D6C6GS58 10K monthly sales, #2 B0CQVWT2NH 8K/month (+20.0% MoM, fastest growing), #3 B0CP9YB3Q4 7K/month | F86: Amazon Best Sellers | G86: https://www.asinsight.com/report/US/pink-tumbler-with-straw | H86: mid-2026 (June-July) | I86: seen in snippet | J86: Amazon Best Sellers: Amazon search 'pink 40 oz tumbler with handle': TaroKitc 40 oz pink tumbler with handle & straw 100+ bought in past month; 'hot pink 40 oz tumbler with handle' listings 100+ bought in past month; another listing 50+ bought at $33.75 (https://www.amazon.com/pink-40-oz-tumbler-handle/s?k=pink+40+oz+tumbler+with+handle) | TikTok Shop: '40oz Pink Checkmate Tumbler by no brand, insulated with handle' listing live on TikTok Shop (sold count not in snippet) (https://shop.tiktok.com/us/pdp/40oz-pink-checkmate-tumbler-by-no-brand-insulated-with-handle/1729540851089379417) | K86: Amazon $33.75 seen on one listing; generic pink 40 oz tumblers B0C338XTYN / B0D5C3F3CQ (price not in snippet) | L86: unknown (CJ listing price not in snippet) | M86: note: sell as generic 40 oz tumbler; never reference Stanley in copy. Avoid 'Barbie pink' wording. | N86: none | O86: The desk-side status object of the corporate girlie; pink handle tumbler is the most-saved prop in pink desk flat lays. | P86: BANK Q11
A87: C086 | B87: Pink 40 oz tumbler accessories kit (bow straw topper, letter charms, silicone boot) | C87: workwear-office | D87: Pink desk essentials / coquette office | E87: AliExpress listing '10pcs Tumbler Accessories Set for 40oz & 30oz Cup with Handle, Coquette Pink Bow Letter Charm Decoration Kit' live (order count not in snippet) | F87: AliExpress | G87: https://www.aliexpress.us/item/3256811930830810.html | H87: seen 27 Sep 2026 | I87: unverified: order count not in snippet | J87: TikTok Shop: 'Pink Cup Accessories Set ... Letter Charms, Bow & Diamond Straw Covers, Glitter Silicone Boot' listing live on TikTok Shop (sold count not in snippet) (https://shop.tiktok.com/us/pdp/pink-cup-accessories-set-for-stanley-tumblers-letters-more/1732274648812983202) | K87: unknown | L87: unknown | M87: note: many listings name Stanley in the title; must be listed as 'fits 40 oz handle tumblers' with no brand name | N87: none | O87: Bow-and-pearl charms make a plain tumbler match the pink desk; tiny, giftable, high margin. | P87: REJECT | Q87: Numeric signal exists but weaker than the 40 kept, or it duplicates a kept product in the same look.
A88: C087 | B88: Pink laptop sleeve 13-14 inch (neoprene or faux-leather with bow) | C88: workwear-office | D88: Legally Blonde work bag essentials / pink office carry | E88: ASINsight 'pink computer case' report: #1 ASIN B0GSR7CXX5 est. 2,000 monthly sales, up 100.0% MoM; top-10 range 200-2,000 monthly sales | F88: Amazon Best Sellers | G88: https://www.asinsight.com/report/US/pink-computer-case | H88: mid-2026 | I88: seen in snippet | J88: Amazon Best Sellers: MOSISO 13.3 in neoprene laptop sleeve, Baby Pink (B01EY70LZ8) 2K+ bought in past month; Cute Kawaii Pink Bow faux-leather 13 in sleeve (B0DJVSL32H) 200+ bought in past month; BAGSMART 13-14 in sleeve 1K+ bought in past month (https://www.amazon.com/pink-laptop-case-13-inch/s?k=pink+laptop+case+13+inch) | TikTok Shop: 'pink macbook air 13 inch case' keyword page: listing 96 sold at $12.17 (-39%, was $19.96); '15.6 inch laptop case pink' 15 sold at $10.69 (https://shop.tiktok.com/us/k/pink-macbook-air-13-inch-case) | K88: TikTok Shop $10.69-$19.96; Amazon puffy pink sleeve $35.71 (TikTok Shop Five Season Home listing) | L88: unknown | M88: note: do not use 'MacBook' or Apple marks in listing title; say 'fits 13-14 inch laptops' | N88: none | O88: The pink bow sleeve is the first thing visible when she pulls her laptop out in a meeting; pure aesthetic signalling. | P88: BANK E06
A89: C088 | B89: Pink puffer / quilted work tote (fits 15.6 inch laptop) | C89: workwear-office | D89: Legally Blonde work bag essentials | E89: ASINsight 'pink puffer tote bag' report: #1 ASIN B0CKYZWDPT 7K monthly sales; B0CS2R1S1B 2K/month; B0DHYZ2GFK 2K/month and fastest growing at +100.0% MoM | F89: Amazon Best Sellers | G89: https://www.asinsight.com/report/US/pink-puffer-tote-bag | H89: mid-2026 | I89: seen in snippet | J89: Amazon Best Sellers: Amazon 'pink laptop tote bag' search: women's tote listing 1K+ bought in past month; laptop tote for women 500+ bought in past month; travel tote 3K+ bought in past month (https://www.amazon.com/pink-laptop-tote-bag/s?k=pink+laptop+tote+bag) | K89: unknown (LOVEVOOK pink 15.6 in leather laptop tote B08QZK3NT2 is the reference listing; price not in snippet) | L89: unknown | M89: none (avoid quilted patterns that copy Chanel-style trade dress) | N89: none | O89: A pink bag big enough for a laptop is the hero of every 'what's in my work bag' pin. | P89: BANK E07
A90: C089 | B90: Pink wooden monitor stand riser with storage drawer (no electronics) | C90: workwear-office | D90: The Law School Desk Setup, All Pink | E90: TEAMIX Pink Monitor Stand Riser, wood with storage (B0CB2YKYST) 50+ bought in past month; 'monitor stand riser wood' category 500+ bought in past month | F90: Amazon Best Sellers | G90: https://www.amazon.com/TEAMIX-Monitor-Storage-Computer-Pink-14-2/dp/B0CB2YKYST | H90: seen 27 Sep 2026 | I90: seen in snippet | K90: unknown (Amazon TEAMIX B0CB2YKYST and 2-pack B09GN1CS6Q; price not in snippet) | L90: AliExpress 'Pink Cute Monitor Stand Desktop Storage Wood Bracket' US$30.50 (32% off) https://www.aliexpress.com/item/1005002392658404.html | M90: none | N90: none | O90: Lifts the monitor and hides cables, and the pink shelf becomes the styling plinth for the whole desk. | P90: BANK E05
A91: C090 | B91: Pink aesthetic sticky notes / transparent sticky note set | C91: workwear-office | D91: The Law School Desk Setup, All Pink / study desk essentials | E91: Amazon 'pink sticky notes' vintage-aesthetic listing 200+ bought in past month; 'pink sticky note set' 200+ bought in past month (lowest price in 30 days); 'aesthetic sticky notes set' 300+ bought in past month | F91: Amazon Best Sellers | G91: https://www.amazon.com/pink-sticky-note-set/s?k=pink+sticky+note+set | H91: seen 27 Sep 2026 | I91: seen in snippet | J91: other: Eprolo 'Top Selling Items on TikTok 2026' lists gel pen sets, highlighter sets and budget planner notebooks as trending office supplies (no number) (https://eprolo.com/top-selling-items-on-tiktok) | K91: unknown | L91: unknown | M91: note: avoid 'Post-it' in copy | N91: none | O91: Low-cost add-on that fills the frame of the pink desk flat lay; bundles with the desk set. | P91: BANK E04
A92: C091 | B92: Pink knit cardigan (office layer, oversized or wrap style) | C92: workwear-office | D92: Legally Blonde Outfits | Pink Amazon Fashion | E92: Keyword page 'style pink cardigan' shows products with sold counts from 23 to 40.8K sold | F92: TikTok Shop | G92: https://shop.tiktok.com/us/k/style-pink-cardigan | H92: seen 27 Sep 2026 | I92: seen in snippet | J92: TikTok Shop: Keyword page 'pink cardigan oversized' listings 9 to 321 sold, prices from $18.99; 'plus size womens clothing pink cardigan' 3 to 261 sold, from about $16-$54 (https://shop.tiktok.com/us/k/pink-cardigan-oversized) | K92: TikTok Shop from $18.99 (oversized) to about $54 (plus size) | L92: unknown | M92: none | N92: none | O92: The over-the-shoulder pink cardigan is the office uniform of the Legally Blonde outfit board. | P92: REJECT | Q92: Sized apparel: returns run well above the 8% allowance and Tommy Kate cannot wear blazers; kept for the Amazon pipeline, not the store.
A93: C092 | B93: Pink cropped blazer | C93: workwear-office | D93: Legally Blonde Outfits | Pink Amazon Fashion | E93: Keyword page 'pink crop blazer outfits' shows listing with 130 sold; 'bright pink blazer plus size' listings 4 to 17 sold | F93: TikTok Shop | G93: https://shop.tiktok.com/us/k/pink-crop-blazer-outfits | H93: seen 27 Sep 2026 | I93: seen in snippet | K93: unknown | L93: unknown | M93: none | N93: none | O93: Hot pink blazer over white is the single most-saved 'Elle Woods at work' outfit image. | P93: REJECT | Q93: Sized apparel: returns run well above the 8% allowance and Tommy Kate cannot wear blazers; kept for the Amazon pipeline, not the store.
A94: C093 | B94: Pink 2026 planner / mini weekly planner with PU leather cover | C94: workwear-office | D94: The Law School Desk Setup, All Pink | E94: 'A7 Mini Weekly Planner 2026 with PU Leather Cover in Pink and Denim Blue' listing live on TikTok Shop (sold count not in snippet); 'BRAVE ELK 2026 Self-Discipline Calendar Planner' pink option shows 2 sold | F94: TikTok Shop | G94: https://shop.tiktok.com/us/pdp/a7-mini-weekly-planner-2026-128-seiten-pu-ledercover/1731486274887192749 | H94: seen 27 Sep 2026 | I94: seen in snippet (2 sold is weak) | J94: Etsy: Etsy market pages '2026 planner pink digital' and 'pink 2026 digital planner' exist with active listings (counts not in snippet) (https://www.etsy.com/market/pink_2026_digital_planner) | K94: unknown (Papier pink 2026 hardback planners are the premium reference https://www.papier.com/us/stationery/calendar-year-planners/pink) | L94: unknown | M94: none | N94: none | O94: Q4 is planner-buying season; a blush planner on the desk mat is the anchor of every 'reset' pin. | P94: REJECT | Q94: Numeric signal exists but weaker than the 40 kept, or it duplicates a kept product in the same look.
A95: C094 | B95: Pink leopard / pink glitter retractable badge reel with card holder | C95: workwear-office | D95: Pink office carry / corporate girlie lanyard | E95: 'Fashionable Sliding Badge Holder Pink Leopard Print ... Retractable Badge Reel Carabiner & Detachable Lanyard' listing live; DeColoresBadges pink glitter badge reel listing live (sold counts not in snippet) | F95: TikTok Shop | G95: https://shop.tiktok.com/us/pdp/pink-leopard-print-badge-holder-with-retractable-reel-lanyard/1732318703040892938 | H95: seen 27 Sep 2026 | I95: unverified: sold count not in snippet | K95: unknown | L95: unknown | M95: note: many top badge reels are Diet Coke / soda-brand themed - hard reject those; keep to plain pink, bow, pearl, leopard | N95: none | O95: Nurses, teachers and office workers all wear one; a pink bow reel is the cheapest way to make the uniform girly. | P95: REJECT | Q95: No numeric signal found (listings exist, counts not visible in snippets).
A96: C095 | B96: Pink laptop stand (aluminium or acrylic riser, no electronics) | C96: workwear-office | D96: The Law School Desk Setup, All Pink | E96: ASINsight publishes dedicated 'pink laptop stand' and 'laptop stand pink' top-10 real-sales reports for 2026 (figures not in snippet) | F96: Amazon Best Sellers | G96: https://www.asinsight.com/report/US/pink-laptop-stand | H96: 2026 | I96: unverified: report exists, numbers not in snippet | K96: unknown | L96: unknown | M96: none | N96: none | O96: Raises the laptop into the frame of the desk photo and matches the pink monitor riser. | P96: REJECT | Q96: Numeric signal exists but weaker than the 40 kept, or it duplicates a kept product in the same look.
A97: C096 | B97: Pink office / pink desk aesthetic (category-level demand signal, use for list titles) | C97: workwear-office | D97: The Law School Desk Setup, All Pink | E97: TikTok tag #pinkoffice: 10.7M posts | F97: other | G97: https://www.tiktok.com/tag/pinkoffice?lang=en | H97: seen 27 Sep 2026 | I97: seen in snippet | J97: Pinterest Predicts: Pinterest Predicts 2026 names 'vintage pink' (with 'moody blue') as a bold colour people want to personalise spaces with; report based on searches Sep 2024-Aug 2025 vs prior year (https://www.nbcnews.com/select/shopping/pinterest-predicts-2026-trend-report-rcna248706) | other: TikTok discover page 'Pink Reception Desk' shows 662.7K posts (https://www.tiktok.com/discover/pink-reception-desk) | K97: n/a | L97: n/a | M97: none | N97: none | O97: Proves the aesthetic itself is a saved category; every product above should be pinned under this look. | P97: REJECT | Q97: Category signal only, used for look titles, not a product.
A98: C097 | B98: NO-SIGNAL SECTION: pink loafers; satin padded pink headband; pearl hair claw / pearl bow clip; pink wide-leg work trousers; pink insulated bottle (non-40oz); pink acrylic file holder / magazine rack; pink highlighter set; pink hardcover notebook / journal; pink pen cup alone; certified pink keyboard/mouse; certified plug-in pink desk lamp | C98: workwear-office | D98: Legally Blonde Outfits | Pink Amazon Fashion / The Law School Desk Setup, All Pink | E98: No numeric signal captured: session web-search budget hit its cap (200/200 shared) before these queries ran. Lead should run: site:shop.tiktok.com [item] sold; asinsight.com/report/US/pink-[item]; Amazon 'bought in past month' | F98: other | H98: 27 Sep 2026 | I98: unverified: not searched | K98: unknown | L98: unknown | M98: none expected; keyboard/mouse/lamp need UL/ETL/FCC proof before listing | N98: keyboard/mouse/lamp are electronics - prefer none per brief | O98: Placeholder so the lead can decide whether to research these separately. | P98: REJECT | Q98: No numeric signal found before the search budget ran out (no signal, no product).
A99: C098 | B99: Pink velvet Christmas tree bows (set of 8-12, wired, for tree tips and garland) | C99: seasonal-christmas | D99: Pink Christmas tree decor list | E99: Pinterest reports searches for 'Red bow Christmas tree' rising by 200% compared to this time last year (bow-tree trend; colour reported was red, not pink) | F99: Pinterest Trends | G99: https://www.idealhome.co.uk/all-rooms/the-updated-christmas-bow-trend-2025 | H99: Christmas 2025 season article (2025) | I99: seen in snippet; attribution to the Ideal Home article among the result set could not be confirmed, WebFetch blocked | J99: Etsy: On Etsy, handmade satin bows have become top-selling seasonal items, with 'velvet Christmas bow set' searches up more than 120% year-over-year (https://pbfulfill.com/blogs/product-recommendation/bow-christmas) | TikTok Shop: 8 Pcs Pink/Silver Velvet Christmas Bows listing, $52.00 + $6.68 shipping, 0 sold, seller Cottage & Calm (price ceiling / competition gap signal, not demand) (https://shop.tiktok.com/us/pdp/8-piece-pink-silver-velvet-christmas-bows-for-tree-gifts/1732139822586630370) | other: Trend commentary: 'rising demand for bows as statement elements, particularly in pink and oversized designs' (no number) (https://www.accio.com/business/bow_christmas_tree_trend) | K99: $52 for an 8-pc pink/silver velvet set on TikTok Shop (0 sold, likely overpriced); Amazon/Etsy comparable sets not priced in snippets | L99: unknown | M99: none | N99: none | O99: The bow tree is the single most-saved Christmas tree look two years running; a pink velvet version is the girly upgrade every pink-home board wants. | P99: BANK Q06
A100: C099 | B100: Pink bow garland (linked satin/velvet bows on ribbon for mantel, tree or staircase) | C100: seasonal-christmas | D100: Pink Christmas tree decor list / Pink mantel | E100: 'Red bow Christmas tree' searches +200% YoY (bow-everything trend; red colourway reported) | F100: Pinterest Trends | G100: https://www.idealhome.co.uk/all-rooms/the-updated-christmas-bow-trend-2025 | H100: 2025 | I100: seen in snippet; article attribution unconfirmed | J100: Etsy: 'velvet Christmas bow set' searches up more than 120% YoY (https://pbfulfill.com/blogs/product-recommendation/bow-christmas) | TikTok Shop: '78.74 Inch Christmas Vine Decoration Set, Garland Ribbon, Bow' product page exists (no sold count visible in snippet) (https://shop.tiktok.com/us/pdp/78-74-inch-christmas-vine-decoration-set-garland-ribbon-bow/1732042411117678871) | K100: unknown | L100: unknown | M100: none | N100: none | O100: One garland turns a plain mantel or staircase into the bow-core Christmas look; pink makes it a Pinkmas hero shot. | P100: BANK Q07
...

Sheet Suppliers
A1: Product ID | B1: Product | C1: Rank | D1: Supplier | E1: Supplier listing URL | F1: Product cost ($) | G1: Ship to GA 31808 ($) | H1: Ship to CA 90210 ($) | I1: Days to GA (min-max) | J1: Days to CA (min-max) | K1: Max quoted days | L1: Warehouse country | M1: MOQ | N1: Packaging | O1: Return policy | P1: Photos usable? | Q1: Verified? | R1: Notes
A2: Q01 | B2: Fluffy pink bunny ears headband | C2: winner | D2: CJ Dropshipping (US warehouse filter) | E2: https://cjdropshipping.com/search/plush+bunny+ears+headband+pink.html | F2: 7.7 | G2: 4.5 | H2: 4.5 | I2: 4 to 9 days (1 to 3 processing + 3 to 6 transit, cjdropshipping.com via snippet) | J2: 4 to 9 days (1 to 3 processing + 3 to 6 transit, cjdropshipping.com via snippet) | K2: 9 | L2: US (NJ or CA) | M2: 1 | N2: unbranded mailer (confirm) | O2: CJ: refund or resend for damaged, wrong or lost items; change-of-mind returns at buyer cost. Confirm on cjdropshipping.com (return policy page). | P2: listing photos usable for the product page after checking the supplier licence; pins use our generated images | Q2: estimate: cost = 40% of the US retail seen (Zendrop guide ratio $8 to $12 product on $25 retail); confirm on cjdropshipping.com | R2: Search 'plush bunny ears headband pink' with the US Warehouse filter on. Shipping: under 8 oz, estimate $4.50 (Zendrop $4 to $6 band). Colour of the 4.8K-sold variant not confirmed pink.
A3: Q01 | B3: Fluffy pink bunny ears headband | C3: backup | D3: Zendrop (Ships From: US filter) | E3: https://app.zendrop.com/ (search 'plush bunny ears headband pink', Ships From: US) | F3: 8.47 | G3: 4.5 | H3: 4.5 | I3: 3 to 11 days (1 to 3 business days processing + 2 to 8 days, support.zendrop.com via snippet) | J3: 3 to 11 days (1 to 3 business days processing + 2 to 8 days, support.zendrop.com via snippet) | K3: 11 | L3: US | M3: 1 | N3: unbranded mailer (confirm) | O3: Zendrop: refund or replacement for damaged or lost orders; change-of-mind returns not covered. Confirm on support.zendrop.com. | P3: listing photos usable for the product page after checking the supplier licence; pins use our generated images | Q3: estimate; confirm on app.zendrop.com | R3: Needs a paid Zendrop plan ($29/month for 1 to 20 linked products). Cost estimate = CJ estimate + 10%. Search 'plush bunny ears headband pink'.
A4: Q01 | B4: Fluffy pink bunny ears headband | C4: last-resort | D4: AliExpress Choice (non-US, last resort) | E4: https://www.aliexpress.us/w/wholesale-plush-bunny-ears-headband-pink.html | F4: 4.62 | G4: 0 | H4: 0 | I4: 7 to 15 days quoted on most Choice listings; exceeds the 10-day rule | J4: 7 to 15 days quoted on most Choice listings; exceeds the 10-day rule | K4: 15 | L4: China | M4: 1 | N4: unbranded mailer (confirm) | O4: AliExpress Choice: free returns within 15 days on Choice items per AliExpress; the store still owes the customer a US return route. Confirm on aliexpress.com. | P4: listing photos usable for the product page after checking the supplier licence; pins use our generated images | Q4: estimate; confirm on aliexpress.com | R4: EXCLUDED for Q4 (15+ day quote). Evergreen only if the US options fail AND margin is 10 points better. Duties apply since de minimis ended 29 Aug 2025.
A5: Q02 | B5: Pink velvet pumpkins, set of 12 | C5: winner | D5: CJ Dropshipping (US warehouse filter) | E5: https://cjdropshipping.com/search/velvet+pumpkin+set+pink+foam.html | F5: 8 | G5: 5.5 | H5: 5.5 | I5: 4 to 9 days (1 to 3 processing + 3 to 6 transit, cjdropshipping.com via snippet) | J5: 4 to 9 days (1 to 3 processing + 3 to 6 transit, cjdropshipping.com via snippet) | K5: 9 | L5: US (NJ or CA) | M5: 1 | N5: unbranded mailer (confirm) | O5: CJ: refund or resend for damaged, wrong or lost items; change-of-mind returns at buyer cost. Confirm on cjdropshipping.com (return policy page). | P5: listing photos usable for the product page after checking the supplier licence; pins use our generated images | Q5: estimate: cost = 40% of the US retail seen (Zendrop guide ratio $8 to $12 product on $25 retail); confirm on cjdropshipping.com | R5: Search 'velvet pumpkin set pink foam' with the US Warehouse filter on. Shipping: 8 oz to 1 lb, estimate $5.50 (CJ 'about $5' example).
A6: Q02 | B6: Pink velvet pumpkins, set of 12 | C6: backup | D6: Zendrop (Ships From: US filter) | E6: https://app.zendrop.com/ (search 'velvet pumpkin set pink foam', Ships From: US) | F6: 8.8 | G6: 5.5 | H6: 5.5 | I6: 3 to 11 days (1 to 3 business days processing + 2 to 8 days, support.zendrop.com via snippet) | J6: 3 to 11 days (1 to 3 business days processing + 2 to 8 days, support.zendrop.com via snippet) | K6: 11 | L6: US | M6: 1 | N6: unbranded mailer (confirm) | O6: Zendrop: refund or replacement for damaged or lost orders; change-of-mind returns not covered. Confirm on support.zendrop.com. | P6: listing photos usable for the product page after checking the supplier licence; pins use our generated images | Q6: estimate; confirm on app.zendrop.com | R6: Needs a paid Zendrop plan ($29/month for 1 to 20 linked products). Cost estimate = CJ estimate + 10%. Search 'velvet pumpkin set pink foam'.
A7: Q02 | B7: Pink velvet pumpkins, set of 12 | C7: last-resort | D7: AliExpress Choice (non-US, last resort) | E7: https://www.aliexpress.com/item/3256804340218119.html | F7: 4.8 | G7: 0 | H7: 0 | I7: 7 to 15 days quoted on most Choice listings; exceeds the 10-day rule | J7: 7 to 15 days quoted on most Choice listings; exceeds the 10-day rule | K7: 15 | L7: China | M7: 1 | N7: unbranded mailer (confirm) | O7: AliExpress Choice: free returns within 15 days on Choice items per AliExpress; the store still owes the customer a US return route. Confirm on aliexpress.com. | P7: listing photos usable for the product page after checking the supplier licence; pins use our generated images | Q7: estimate; confirm on aliexpress.com | R7: EXCLUDED for Q4 (15+ day quote). Evergreen only if the US options fail AND margin is 10 points better. Duties apply since de minimis ended 29 Aug 2025.
A8: Q03 | B8: Pink faux fur throw blanket, 50 by 60 | C8: winner | D8: CJ Dropshipping (US warehouse filter) | E8: https://cjdropshipping.com/search/faux+fur+throw+blanket+pink+50x60.html | F8: 12 | G8: 8.15 | H8: 8.15 | I8: 4 to 9 days (1 to 3 processing + 3 to 6 transit, cjdropshipping.com via snippet) | J8: 4 to 9 days (1 to 3 processing + 3 to 6 transit, cjdropshipping.com via snippet) | K8: 9 | L8: US (NJ or CA) | M8: 1 | N8: unbranded mailer (confirm) | O8: CJ: refund or resend for damaged, wrong or lost items; change-of-mind returns at buyer cost. Confirm on cjdropshipping.com (return policy page). | P8: listing photos usable for the product page after checking the supplier licence; pins use our generated images | Q8: estimate: cost = 40% of the US retail seen (Zendrop guide ratio $8 to $12 product on $25 retail); confirm on cjdropshipping.com | R8: Search 'faux fur throw blanket pink 50x60' with the US Warehouse filter on. Shipping: 1 to 2 lb, USPS Ground Advantage commercial 1 lb zone 4 $8.15 seen.
A9: Q03 | B9: Pink faux fur throw blanket, 50 by 60 | C9: backup | D9: Zendrop (Ships From: US filter) | E9: https://app.zendrop.com/ (search 'faux fur throw blanket pink 50x60', Ships From: US) | F9: 13.2 | G9: 8.15 | H9: 8.15 | I9: 3 to 11 days (1 to 3 business days processing + 2 to 8 days, support.zendrop.com via snippet) | J9: 3 to 11 days (1 to 3 business days processing + 2 to 8 days, support.zendrop.com via snippet) | K9: 11 | L9: US | M9: 1 | N9: unbranded mailer (confirm) | O9: Zendrop: refund or replacement for damaged or lost orders; change-of-mind returns not covered. Confirm on support.zendrop.com. | P9: listing photos usable for the product page after checking the supplier licence; pins use our generated images | Q9: estimate; confirm on app.zendrop.com | R9: Needs a paid Zendrop plan ($29/month for 1 to 20 linked products). Cost estimate = CJ estimate + 10%. Search 'faux fur throw blanket pink 50x60'.
A10: Q03 | B10: Pink faux fur throw blanket, 50 by 60 | C10: last-resort | D10: AliExpress Choice (non-US, last resort) | E10: https://www.aliexpress.us/w/wholesale-faux-fur-throw-blanket-pink-50x60.html | F10: 7.2 | G10: 0 | H10: 0 | I10: 7 to 15 days quoted on most Choice listings; exceeds the 10-day rule | J10: 7 to 15 days quoted on most Choice listings; exceeds the 10-day rule | K10: 15 | L10: China | M10: 1 | N10: unbranded mailer (confirm) | O10: AliExpress Choice: free returns within 15 days on Choice items per AliExpress; the store still owes the customer a US return route. Confirm on aliexpress.com. | P10: listing photos usable for the product page after checking the supplier licence; pins use our generated images | Q10: estimate; confirm on aliexpress.com | R10: EXCLUDED for Q4 (15+ day quote). Evergreen only if the US options fail AND margin is 10 points better. Duties apply since de minimis ended 29 Aug 2025.
A11: Q04 | B11: Pink velvet throw pillow covers, pair | C11: winner | D11: CJ Dropshipping (US warehouse filter) | E11: https://cjdropshipping.com/search/velvet+pillow+cover+pink+18x18.html | F11: 6 | G11: 4.5 | H11: 4.5 | I11: 4 to 9 days (1 to 3 processing + 3 to 6 transit, cjdropshipping.com via snippet) | J11: 4 to 9 days (1 to 3 processing + 3 to 6 transit, cjdropshipping.com via snippet) | K11: 9 | L11: US (NJ or CA) | M11: 1 | N11: unbranded mailer (confirm) | O11: CJ: refund or resend for damaged, wrong or lost items; change-of-mind returns at buyer cost. Confirm on cjdropshipping.com (return policy page). | P11: listing photos usable for the product page after checking the supplier licence; pins use our generated images | Q11: estimate: cost = 40% of the US retail seen (Zendrop guide ratio $8 to $12 product on $25 retail); confirm on cjdropshipping.com | R11: Search 'velvet pillow cover pink 18x18' with the US Warehouse filter on. Shipping: under 8 oz, estimate $4.50 (Zendrop $4 to $6 band).
A12: Q04 | B12: Pink velvet throw pillow covers, pair | C12: backup | D12: Zendrop (Ships From: US filter) | E12: https://app.zendrop.com/ (search 'velvet pillow cover pink 18x18', Ships From: US) | F12: 6.6 | G12: 4.5 | H12: 4.5 | I12: 3 to 11 days (1 to 3 business days processing + 2 to 8 days, support.zendrop.com via snippet) | J12: 3 to 11 days (1 to 3 business days processing + 2 to 8 days, support.zendrop.com via snippet) | K12: 11 | L12: US | M12: 1 | N12: unbranded mailer (confirm) | O12: Zendrop: refund or replacement for damaged or lost orders; change-of-mind returns not covered. Confirm on support.zendrop.com. | P12: listing photos usable for the product page after checking the supplier licence; pins use our generated images | Q12: estimate; confirm on app.zendrop.com | R12: Needs a paid Zendrop plan ($29/month for 1 to 20 linked products). Cost estimate = CJ estimate + 10%. Search 'velvet pillow cover pink 18x18'.
A13: Q04 | B13: Pink velvet throw pillow covers, pair | C13: last-resort | D13: AliExpress Choice (non-US, last resort) | E13: https://www.aliexpress.us/w/wholesale-velvet-pillow-cover-pink-18x18.html | F13: 3.6 | G13: 0 | H13: 0 | I13: 7 to 15 days quoted on most Choice listings; exceeds the 10-day rule | J13: 7 to 15 days quoted on most Choice listings; exceeds the 10-day rule | K13: 15 | L13: China | M13: 1 | N13: unbranded mailer (confirm) | O13: AliExpress Choice: free returns within 15 days on Choice items per AliExpress; the store still owes the customer a US return route. Confirm on aliexpress.com. | P13: listing photos usable for the product page after checking the supplier licence; pins use our generated images | Q13: estimate; confirm on aliexpress.com | R13: EXCLUDED for Q4 (15+ day quote). Evergreen only if the US options fail AND margin is 10 points better. Duties apply since de minimis ended 29 Aug 2025.
... A121: E24 | B121: Cream hooded wearable blanket | C121: last-resort | D121: AliExpress Choice (non-US, last resort) | E121: https://www.aliexpress.us/w/wholesale-hooded-wearable-blanket-fleece-cream.html | F121: 5.4 | G121: 0 | H121: 0 | I121: 7 to 15 days quoted on most Choice listings; exceeds the 10-day rule | J121: 7 to 15 days quoted on most Choice listings; exceeds the 10-day rule | K121: 15 | L121: China | M121: 1 | N121: unbranded mailer (confirm) | O121: AliExpress Choice: free returns within 15 days on Choice items per AliExpress; the store still owes the customer a US return route. Confirm on aliexpress.com. | P121: listing photos usable for the product page after checking the supplier licence; pins use our generated images | Q121: estimate; confirm on aliexpress.com | R121: EXCLUDED for Q4 (15+ day quote). Evergreen only if the US options fail AND margin is 10 points better. Duties apply since de minimis ended 29 Aug 2025.

Sheet Margins
A1: ASSUMPTIONS (blue cells are inputs; change them and every row recalculates)
A2: Orders per month (amortisation base) | B2: 30 | C2: Job D1 brief assumes 30 orders/month
A3: Platform monthly fee ($) | B3: 39 | C3: Shopify Basic, monthly billing, $39/month (help.shopify.com Basic plan page via search snippet, 2026; $1/month for the first 3 months intro offer not modelled). Confirm on shopify.com/pricing.
A4: Fulfilment app monthly fee ($) | B4: 0 | C4: CJ Dropshipping Shopify app: no subscription fee (cjdropshipping.com blog and revenuegeeks, 2026, via snippet). If Zendrop is used instead, enter 29 (1 to 20 linked products) or 49 (21 to 100 products, usage-based billing per support.zendrop.com).
A5: Payment processing rate | B5: 0.029 | C5: 2.9% per the brief (Shopify Payments Basic online rate, confirm on shopify.com/pricing)
A6: Payment processing fixed ($) | B6: 0.3 | C6: $0.30 per the brief
A7: Return allowance (share of price) | B7: 0.08 | C7: 8% of sale price per the brief
A8: Packaging per order ($) | B8: 0.5 | C8: CJ US warehouse ships in its own unbranded mailer at no extra fee (revenuegeeks CJ pricing page via snippet); $0.50 covers an insert card or tissue. Confirm on cjdropshipping.com/service-fee.
A9: CAC scenario 2 ($ per order) | B9: 5 | C9: $5 CAC scenario per the brief; scenario 1 is $0 (Pinterest and email traffic)
A10: Margin floor at $0 CAC | B10: 0.45 | C10: 45% per the brief
A11: Margin floor at $5 CAC | B11: 0.25 | C11: 25% per the brief
A12: Price band: core ceiling ($) | B12: 50 | C12: Pink Finds price bands: the growth plan copy in the repo names no dollar bands, so the factory's price rule is used (section 3: mostly under $50, one splurge per look; window 5: 'under 25' gift guides). Flagged in REPORT.md.
A13: Price band: splurge ceiling ($) | B13: 79 | C13: one splurge allowed per look (factory section 3)
A15: Fixed monthly cost ($) = platform + app | B15: =B3+B4 -> 39
A16: Fee share per order ($) = fixed / orders | B16: =B15/B2 -> 1.3
A17: Sales tax: collected at checkout from the buyer and remitted; not a cost line. Nexus: Georgia on day one (see LEGAL_SETUP_CHECKLIST.md).
A19: ID | B19: Product | C19: Winner supplier | D19: Warehouse | E19: Product cost ($) | F19: Inbound shipping ($) | G19: Packaging ($) | H19: Sale price ($) | I19: Payment processing ($) | J19: App fee share ($) | K19: Return allowance ($) | L19: CAC scenario 1 ($) | M19: CAC scenario 2 ($) | N19: Total cost @ $0 CAC ($) | O19: Gross margin $ @ $0 CAC | P19: Gross margin % @ $0 CAC | Q19: Gross margin $ @ $5 CAC | R19: Gross margin % @ $5 CAC | S19: Break-even units/month | T19: Passes floors? | U19: Free shipping folded in? | V19: Price band | W19: Band OK? | X19: Verified?
A20: Q01 | B20: Fluffy pink bunny ears headband | C20: CJ Dropshipping (US warehouse filter) | D20: US (NJ or CA) | E20: 7.7 | F20: 4.5 | G20: =$B$8 -> 0.5 | H20: 32.99 | I20: =H20*$B$5+$B$6 -> 1.25671 | J20: =$B$16 -> 1.3 | K20: =H20*$B$7 -> 2.6392 | L20: 0 | M20: =$B$9 -> 5 | N20: =E20+F20+G20+I20+J20+K20+L20 -> 17.89591 | O20: =H20-N20 -> 15.09409 | P20: =IF(H20=0,0,O20/H20) -> 0.45753531 | Q20: =O20-M20 -> 10.09409 | R20: =IF(H20=0,0,Q20/H20) -> 0.30597423 | S20: =IF((H20-E20-F20-G20-I20-K20)<=0,"never",ROUNDUP($B$15/(H20-E20-F20-G20-I20-K20),0)) -> 3 | T20: =IF(AND(P20>=$B$10,R20>=$B$11),"PASS","KILL") -> PASS | U20: yes, folded into price | V20: core (under $50) | W20: =IF(H20<=$B$12,"core",IF(H20<=$B$13,"splurge","OUT OF BAND")) -> core | X20: estimate: cost = 40% of the US retail seen (Zendrop guide ratio $8 to $12 product on $25 retail); confirm on cjdropshipping.com
A21: Q02 | B21: Pink velvet pumpkins, set of 12 | C21: CJ Dropshipping (US warehouse filter) | D21: US (NJ or CA) | E21: 8 | F21: 5.5 | G21: =$B$8 -> 0.5 | H21: 35.99 | I21: =H21*$B$5+$B$6 -> 1.34371 | J21: =$B$16 -> 1.3 | K21: =H21*$B$7 -> 2.8792 | L21: 0 | M21: =$B$9 -> 5 | N21: =E21+F21+G21+I21+J21+K21+L21 -> 19.52291 | O21: =H21-N21 -> 16.46709 | P21: =IF(H21=0,0,O21/H21) -> 0.45754626 | Q21: =O21-M21 -> 11.46709 | R21: =IF(H21=0,0,Q21/H21) -> 0.31861878 | S21: =IF((H21-E21-F21-G21-I21-K21)<=0,"never",ROUNDUP($B$15/(H21-E21-F21-G21-I21-K21),0)) -> 3 | T21: =IF(AND(P21>=$B$10,R21>=$B$11),"PASS","KILL") -> PASS | U21: yes, folded into price | V21: core (under $50) | W21: =IF(H21<=$B$12,"core",IF(H21<=$B$13,"splurge","OUT OF BAND")) -> core | X21: estimate: cost = 40% of the US retail seen (Zendrop guide ratio $8 to $12 product on $25 retail); confirm on cjdropshipping.com
A22: Q03 | B22: Pink faux fur throw blanket, 50 by 60 | C22: CJ Dropshipping (US warehouse filter) | D22: US (NJ or CA) | E22: 12 | F22: 8.15 | G22: =$B$8 -> 0.5 | H22: 50.99 | I22: =H22*$B$5+$B$6 -> 1.77871 | J22: =$B$16 -> 1.3 | K22: =H22*$B$7 -> 4.0792 | L22: 0 | M22: =$B$9 -> 5 | N22: =E22+F22+G22+I22+J22+K22+L22 -> 27.80791 | O22: =H22-N22 -> 23.18209 | P22: =IF(H22=0,0,O22/H22) -> 0.45463993 | Q22: =O22-M22 -> 18.18209 | R22: =IF(H22=0,0,Q22/H22) -> 0.35658149 | S22: =IF((H22-E22-F22-G22-I22-K22)<=0,"never",ROUNDUP($B$15/(H22-E22-F22-G22-I22-K22),0)) -> 2 | T22: =IF(AND(P22>=$B$10,R22>=$B$11),"PASS","KILL") -> PASS | U22: yes, folded into price | V22: splurge (one per look) | W22: =IF(H22<=$B$12,"core",IF(H22<=$B$13,"splurge","OUT OF BAND")) -> splurge | X22: estimate: cost = 40% of the US retail seen (Zendrop guide ratio $8 to $12 product on $25 retail); confirm on cjdropshipping.com
A23: Q04 | B23: Pink velvet throw pillow covers, pair | C23: CJ Dropshipping (US warehouse filter) | D23: US (NJ or CA) | E23: 6 | F23: 4.5 | G23: =$B$8 -> 0.5 | H23: 28.99 | I23: =H23*$B$5+$B$6 -> 1.14071 | J23: =$B$16 -> 1.3 | K23: =H23*$B$7 -> 2.3192 | L23: 0 | M23: =$B$9 -> 5 | N23: =E23+F23+G23+I23+J23+K23+L23 -> 15.75991 | O23: =H23-N23 -> 13.23009 | P23: =IF(H23=0,0,O23/H23) -> 0.45636737 | Q23: =O23-M23 -> 8.23009 | R23: =IF(H23=0,0,Q23/H23) -> 0.2838941 | S23: =IF((H23-E23-F23-G23-I23-K23)<=0,"never",ROUNDUP($B$15/(H23-E23-F23-G23-I23-K23),0)) -> 3 | T23: =IF(AND(P23>=$B$10,R23>=$B$11),"PASS","KILL") -> PASS | U23: yes, folded into price | V23: core (under $50) | W23: =IF(H23<=$B$12,"core",IF(H23<=$B$13,"splurge","OUT OF BAND")) -> core | X23: estimate: cost = 40% of the US retail seen (Zendrop guide ratio $8 to $12 product on $25 retail); confirm on cjdropshipping.com
A24: Q05 | B24: Pink reusable party cups, 16 oz pack | C24: CJ Dropshipping (US warehouse filter) | D24: US (NJ or CA) | E24: 10.4 | F24: 5.5 | G24: =$B$8 -> 0.5 | H24: 40.99 | I24: =H24*$B$5+$B$6 -> 1.48871 | J24: =$B$16 -> 1.3 | K24: =H24*$B$7 -> 3.2792 | L24: 0 | M24: =$B$9 -> 5 | N24: =E24+F24+G24+I24+J24+K24+L24 -> 22.46791 | O24: =H24-N24 -> 18.52209 | P24: =IF(H24=0,0,O24/H24) -> 0.4518685 | Q24: =O24-M24 -> 13.52209 | R24: =IF(H24=0,0,Q24/H24) -> 0.32988753 | S24: =IF((H24-E24-F24-G24-I24-K24)<=0,"never",ROUNDUP($B$15/(H24-E24-F24-G24-I24-K24),0)) -> 2 | T24: =IF(AND(P24>=$B$10,R24>=$B$11),"PASS","KILL") -> PASS | U24: yes, folded into price | V24: core (under $50) | W24: =IF(H24<=$B$12,"core",IF(H24<=$B$13,"splurge","OUT OF BAND")) -> core | X24: estimate: cost = 40% of the US retail seen (Zendrop guide ratio $8 to $12 product on $25 retail); confirm on cjdropshipping.com
A25: Q06 | B25: Pink velvet Christmas tree bows, 24 pack | C25: CJ Dropshipping (US warehouse filter) | D25: US (NJ or CA) | E25: 7 | F25: 5.5 | G25: =$B$8 -> 0.5 | H25: 33.99 | I25: =H25*$B$5+$B$6 -> 1.28571 | J25: =$B$16 -> 1.3 | K25: =H25*$B$7 -> 2.7192 | L25: 0 | M25: =$B$9 -> 5 | N25: =E25+F25+G25+I25+J25+K25+L25 -> 18.30491 | O25: =H25-N25 -> 15.68509 | P25: =IF(H25=0,0,O25/H25) -> 0.4614619 | Q25: =O25-M25 -> 10.68509 | R25: =IF(H25=0,0,Q25/H25) -> 0.31435981 | S25: =IF((H25-E25-F25-G25-I25-K25)<=0,"never",ROUNDUP($B$15/(H25-E25-F25-G25-I25-K25),0)) -> 3 | T25: =IF(AND(P25>=$B$10,R25>=$B$11),"PASS","KILL") -> PASS | U25: yes, folded into price | V25: core (under $50) | W25: =IF(H25<=$B$12,"core",IF(H25<=$B$13,"splurge","OUT OF BAND")) -> core | X25: estimate: cost = 40% of the US retail seen (Zendrop guide ratio $8 to $12 product on $25 retail); confirm on cjdropshipping.com
A26: Q07 | B26: Pink velvet bow garland, 6 ft | C26: CJ Dropshipping (US warehouse filter) | D26: US (NJ or CA) | E26: 8 | F26: 5.5 | G26: =$B$8 -> 0.5 | H26: 35.99 | I26: =H26*$B$5+$B$6 -> 1.34371 | J26: =$B$16 -> 1.3 | K26: =H26*$B$7 -> 2.8792 | L26: 0 | M26: =$B$9 -> 5 | N26: =E26+F26+G26+I26+J26+K26+L26 -> 19.52291 | O26: =H26-N26 -> 16.46709 | P26: =IF(H26=0,0,O26/H26) -> 0.45754626 | Q26: =O26-M26 -> 11.46709 | R26: =IF(H26=0,0,Q26/H26) -> 0.31861878 | S26: =IF((H26-E26-F26-G26-I26-K26)<=0,"never",ROUNDUP($B$15/(H26-E26-F26-G26-I26-K26),0)) -> 3 | T26: =IF(AND(P26>=$B$10,R26>=$B$11),"PASS","KILL") -> PASS | U26: yes, folded into price | V26: core (under $50) | W26: =IF(H26<=$B$12,"core",IF(H26<=$B$13,"splurge","OUT OF BAND")) -> core | X26: estimate: cost = 40% of the US retail seen (Zendrop guide ratio $8 to $12 product on $25 retail); confirm on cjdropshipping.com
A27: Q08 | B27: Pink shatterproof ornament set, 45 pieces | C27: CJ Dropshipping (US warehouse filter) | D27: US (NJ or CA) | E27: 9 | F27: 8.15 | G27: =$B$8 -> 0.5 | H27: 43.99 | I27: =H27*$B$5+$B$6 -> 1.57571 | J27: =$B$16 -> 1.3 | K27: =H27*$B$7 -> 3.5192 | L27: 0 | M27: =$B$9 -> 5 | N27: =E27+F27+G27+I27+J27+K27+L27 -> 24.04491 | O27: =H27-N27 -> 19.94509 | P27: =IF(H27=0,0,O27/H27) -> 0.45340055 | Q27: =O27-M27 -> 14.94509 | R27: =IF(H27=0,0,Q27/H27) -> 0.33973835 | S27: =IF((H27-E27-F27-G27-I27-K27)<=0,"never",ROUNDUP($B$15/(H27-E27-F27-G27-I27-K27),0)) -> 2 | T27: =IF(AND(P27>=$B$10,R27>=$B$11),"PASS","KILL") -> PASS | U27: yes, folded into price | V27: core (under $50) | W27: =IF(H27<=$B$12,"core",IF(H27<=$B$13,"splurge","OUT OF BAND")) -> core | X27: estimate: cost = 40% of the US retail seen (Zendrop guide ratio $8 to $12 product on $25 retail); confirm on cjdropshipping.com
A28: Q09 | B28: Pink velvet Christmas stocking with bow | C28: CJ Dropshipping (US warehouse filter) | D28: US (NJ or CA) | E28: 5 | F28: 4.5 | G28: =$B$8 -> 0.5 | H28: 26.99 | I28: =H28*$B$5+$B$6 -> 1.08271 | J28: =$B$16 -> 1.3 | K28: =H28*$B$7 -> 2.1592 | L28: 0 | M28: =$B$9 -> 5 | N28: =E28+F28+G28+I28+J28+K28+L28 -> 14.54191 | O28: =H28-N28 -> 12.44809 | P28: =IF(H28=0,0,O28/H28) -> 0.46121119 | Q28: =O28-M28 -> 7.44809 | R28: =IF(H28=0,0,Q28/H28) -> 0.27595739 | S28: =IF((H28-E28-F28-G28-I28-K28)<=0,"never",ROUNDUP($B$15/(H28-E28-F28-G28-I28-K28),0)) -> 3 | T28: =IF(AND(P28>=$B$10,R28>=$B$11),"PASS","KILL") -> PASS | U28: yes, folded into price | V28: core (under $50) | W28: =IF(H28<=$B$12,"core",IF(H28<=$B$13,"splurge","OUT OF BAND")) -> core | X28: estimate: cost = 40% of the US retail seen (Zendrop guide ratio $8 to $12 product on $25 retail); confirm on cjdropshipping.com
A29: Q10 | B29: Pink flocked tabletop Christmas tree, 2 ft, unlit | C29: CJ Dropshipping (US warehouse filter) | D29: US (NJ or CA) | E29: 12 | F29: 8.15 | G29: =$B$8 -> 0.5 | H29: 50.99 | I29: =H29*$B$5+$B$6 -> 1.77871 | J29: =$B$16 -> 1.3 | K29: =H29*$B$7 -> 4.0792 | L29: 0 | M29: =$B$9 -> 5 | N29: =E29+F29+G29+I29+J29+K29+L29 -> 27.80791 | O29: =H29-N29 -> 23.18209 | P29: =IF(H29=0,0,O29/H29) -> 0.45463993 | Q29: =O29-M29 -> 18.18209 | R29: =IF(H29=0,0,Q29/H29) -> 0.35658149 | S29: =IF((H29-E29-F29-G29-I29-K29)<=0,"never",ROUNDUP($B$15/(H29-E29-F29-G29-I29-K29),0)) -> 2 | T29: =IF(AND(P29>=$B$10,R29>=$B$11),"PASS","KILL") -> PASS | U29: yes, folded into price | V29: splurge (one per look) | W29: =IF(H29<=$B$12,"core",IF(H29<=$B$13,"splurge","OUT OF BAND")) -> splurge | X29: estimate: cost = 40% of the US retail seen (Zendrop guide ratio $8 to $12 product on $25 retail); confirm on cjdropshipping.com
A30: Q11 | B30: Pink 40 oz insulated tumbler with handle and straw | C30: CJ Dropshipping (US warehouse filter) | D30: US (NJ or CA) | E30: 9 | F30: 8.15 | G30: =$B$8 -> 0.5 | H30: 43.99 | I30: =H30*$B$5+$B$6 -> 1.57571 | J30: =$B$16 -> 1.3 | K30: =H30*$B$7 -> 3.5192 | L30: 0 | M30: =$B$9 -> 5 | N30: =E30+F30+G30+I30+J30+K30+L30 -> 24.04491 | O30: =H30-N30 -> 19.94509 | P30: =IF(H30=0,0,O30/H30) -> 0.45340055 | Q30: =O30-M30 -> 14.94509 | R30: =IF(H30=0,0,Q30/H30) -> 0.33973835 | S30: =IF((H30-E30-F30-G30-I30-K30)<=0,"never",ROUNDUP($B$15/(H30-E30-F30-G30-I30-K30),0)) -> 2 | T30: =IF(AND(P30>=$B$10,R30>=$B$11),"PASS","KILL") -> PASS | U30: yes, folded into price | V30: core (under $50) | W30: =IF(H30<=$B$12,"core",IF(H30<=$B$13,"splurge","OUT OF BAND")) -> core | X30: listing found via search; price not visible in snippet, cost is an estimate; confirm on cjdropshipping.com
A31: Q12 | B31: Pink velvet jewelry box with lock | C31: CJ Dropshipping (US warehouse filter) | D31: US (NJ or CA) | E31: 10 | F31: 5.5 | G31: =$B$8 -> 0.5 | H31: 39.99 | I31: =H31*$B$5+$B$6 -> 1.45971 | J31: =$B$16 -> 1.3 | K31: =H31*$B$7 -> 3.1992 | L31: 0 | M31: =$B$9 -> 5 | N31: =E31+F31+G31+I31+J31+K31+L31 -> 21.95891 | O31: =H31-N31 -> 18.03109 | P31: =IF(H31=0,0,O31/H31) -> 0.45088997 | Q31: =O31-M31 -> 13.03109 | R31: =IF(H31=0,0,Q31/H31) -> 0.32585871 | S31: =IF((H31-E31-F31-G31-I31-K31)<=0,"never",ROUNDUP($B$15/(H31-E31-F31-G31-I31-K31),0)) -> 3 | T31: =IF(AND(P31>=$B$10,R31>=$B$11),"PASS","KILL") -> PASS | U31: yes, folded into price | V31: core (under $50) | W31: =IF(H31<=$B$12,"core",IF(H31<=$B$13,"splurge","OUT OF BAND")) -> core | X31: estimate: cost = 40% of the US retail seen (Zendrop guide ratio $8 to $12 product on $25 retail); confirm on cjdropshipping.com
... A59: E24 | B59: Cream hooded wearable blanket | C59: CJ Dropshipping (US warehouse filter) | D59: US (NJ or CA) | E59: 9 | F59: 8.15 | G59: =$B$8 -> 0.5 | H59: 43.99 | I59: =H59*$B$5+$B$6 -> 1.57571 | J59: =$B$16 -> 1.3 | K59: =H59*$B$7 -> 3.5192 | L59: 0 | M59: =$B$9 -> 5 | N59: =E59+F59+G59+I59+J59+K59+L59 -> 24.04491 | O59: =H59-N59 -> 19.94509 | P59: =IF(H59=0,0,O59/H59) -> 0.45340055 | Q59: =O59-M59 -> 14.94509 | R59: =IF(H59=0,0,Q59/H59) -> 0.33973835 | S59: =IF((H59-E59-F59-G59-I59-K59)<=0,"never",ROUNDUP($B$15/(H59-E59-F59-G59-I59-K59),0)) -> 2 | T59: =IF(AND(P59>=$B$10,R59>=$B$11),"PASS","KILL") -> PASS | U59: yes, folded into price | V59: core (under $50) | W59: =IF(H59<=$B$12,"core",IF(H59<=$B$13,"splurge","OUT OF BAND")) -> core | X59: estimate: cost = 40% of the US retail seen (Zendrop guide ratio $8 to $12 product on $25 retail); confirm on cjdropshipping.com
A61: Notes
A62: Break-even units/month = fixed monthly cost / (price minus product, inbound shipping, packaging, processing and return allowance). It answers: how many orders a month before the platform and app fees are covered.
A63: App fee share = (platform + app monthly) / orders per month, so it already sits inside every unit's cost; break-even is the second way of looking at the same fixed cost.
A64: Inbound shipping is the winner supplier's quoted shipping to Georgia (the higher of GA/CA is used where they differ; see Suppliers sheet).
A65: Every supplier cost and shipping figure is from search results only (this container cannot open supplier sites); confirm each on the supplier site before pricing goes live. See the Verified? column.

Sheet Bank40
A1: ID | B1: Product | C1: Bank | D1: Season / window | E1: Look (slug) | F1: Look title | G1: Category | H1: Colour role | I1: Winner supplier | J1: Warehouse | K1: Delivery window (customer copy) | L1: Backup supplier | M1: Sale price ($) | N1: Gross margin % @ $0 CAC | O1: Gross margin % @ $5 CAC | P1: Viral evidence | Q1: Why it will pin | R1: Verified?
A2: Q01 | B2: Fluffy pink bunny ears headband | C2: Q4 | D2: Halloween | E2: pink-halloween-party-at-home-last-call | F2: Pink Halloween Party at Home, Last Call | G2: home-decor | H2: hero pink | I2: CJ Dropshipping (US warehouse filter) | J2: US (NJ or CA) | K2: Ships from our US warehouse in 4 to 9 business days | L2: Zendrop (Ships From: US filter) | M2: =Margins!H20 -> 32.99 | N2: =Margins!P20 -> 0.45753531 | O2: =Margins!R20 -> 0.30597423 | P2: TikTok Shop keyword page 'bunny fluffy ears': listing with 4.8K sold at $19.28 (seen in snippet, 27 Sep 2026) https://shop.tiktok.com/us/k/bunny-fluffy-ears | Q2: The one costume piece that turns a black dress into a party outfit in four seconds, and it goes back in the drawer for Easter. | R2: estimate: cost = 40% of the US retail seen (Zendrop guide ratio $8 to $12 product on $25 retail); confirm on cjdropshipping.com
A3: Q02 | B3: Pink velvet pumpkins, set of 12 | C3: Q4 | D3: Halloween | E3: pink-halloween-party-at-home-last-call | F3: Pink Halloween Party at Home, Last Call | G3: home-decor | H3: hero pink | I3: CJ Dropshipping (US warehouse filter) | J3: US (NJ or CA) | K3: Ships from our US warehouse in 4 to 9 business days | L3: Zendrop (Ships From: US filter) | M3: =Margins!H21 -> 35.99 | N3: =Margins!P21 -> 0.45754626 | O3: =Margins!R21 -> 0.31861878 | P3: Amazon search 'pink velvet pumpkins': listings show 50+ and 100+ bought in past month (Winlyn 7-pc, Amandir 16-pc, Havawish 16-pc) (seen in snippet, 27 Sep 2026) https://www.amazon.com/velvet-pumpkins/s?k=velvet+pumpkins; AliExpress listing 3256804340218119 exists (orders not visible) | Q3: Velvet pumpkins are the pink Halloween decor that still looks right on the Thanksgiving table, so they earn for eight weeks instead of three. | R3: estimate: cost = 40% of the US retail seen (Zendrop guide ratio $8 to $12 product on $25 retail); confirm on cjdropshipping.com
A4: Q03 | B4: Pink faux fur throw blanket, 50 by 60 | C4: Q4 | D4: Halloween | E4: pink-halloween-party-at-home-last-call | F4: Pink Halloween Party at Home, Last Call | G4: home-decor | H4: supporting pink | I4: CJ Dropshipping (US warehouse filter) | J4: US (NJ or CA) | K4: Ships from our US warehouse in 4 to 9 business days | L4: Zendrop (Ships From: US filter) | M4: =Margins!H22 -> 50.99 | N4: =Margins!P22 -> 0.45463993 | O4: =Margins!R22 -> 0.35658149 | P4: Amazon 'pink faux fur throw blanket': Jungle Star 50x60 100+ bought in past month, Amazon's Choice (seen in snippet, 27 Sep 2026) https://www.amazon.com/pink-fluffy-blanket/s?k=pink+fluffy+blanket; TikTok Shop 'pink blanket fluffy' keyword page notes blankets that 'sold thousands' (unverified) | Q4: The blanket is what makes a movie-night pin look like a room you want to be in, and pink faux fur photographs like a cloud. | R4: estimate: cost = 40% of the US retail seen (Zendrop guide ratio $8 to $12 product on $25 retail); confirm on cjdropshipping.com
A5: Q04 | B5: Pink velvet throw pillow covers, pair | C5: Q4 | D5: Halloween | E5: pink-halloween-party-at-home-last-call | F5: Pink Halloween Party at Home, Last Call | G5: home-decor | H5: supporting pink | I5: CJ Dropshipping (US warehouse filter) | J5: US (NJ or CA) | K5: Ships from our US warehouse in 4 to 9 business days | L5: Zendrop (Ships From: US filter) | M5: =Margins!H23 -> 28.99 | N5: =Margins!P23 -> 0.45636737 | O5: =Margins!R23 -> 0.2838941 | P5: Amazon 'pink velvet pillows' 200+ bought in past month; 'pink velvet pillow cover' 50+; 'velvet throw pillow covers' 800+ (seen in snippet, 27 Sep 2026) https://www.amazon.com/Pink-Velvet-Pillows/s?k=Pink+Velvet+Pillows | Q5: Covers, not pillows, so they ship flat and cheap, and swapping two covers is the cheapest room change on the internet. | R5: estimate: cost = 40% of the US retail seen (Zendrop guide ratio $8 to $12 product on $25 retail); confirm on cjdropshipping.com
A6: Q05 | B6: Pink reusable party cups, 16 oz pack | C6: Q4 | D6: Halloween | E6: pink-halloween-party-at-home-last-call | F6: Pink Halloween Party at Home, Last Call | G6: home-decor | H6: neutral (clear pink acrylic) | I6: CJ Dropshipping (US warehouse filter) | J6: US (NJ or CA) | K6: Ships from our US warehouse in 4 to 9 business days | L6: Zendrop (Ships From: US filter) | M6: =Margins!H24 -> 40.99 | N6: =Margins!P24 -> 0.4518685 | O6: =Margins!R24 -> 0.32988753 | P6: TikTok Shop keyword page 'pink solo cups': 1.9K sold at $25.99 (seen in snippet, 27 Sep 2026) https://shop.tiktok.com/us/k/pink-solo-cups. IP note: 'Solo' is a trademark; sell as pink party cups. | Q6: Every Halloween party photo has a cup in it. Make it pink and reusable and the pin works for Galentine's too. | R6: estimate: cost = 40% of the US retail seen (Zendrop guide ratio $8 to $12 product on $25 retail); confirm on cjdropshipping.com
A7: Q06 | B7: Pink velvet Christmas tree bows, 24 pack | C7: Q4 | D7: Christmas | E7: the-pink-christmas-tree-edit | F7: The Pink Christmas Tree Edit | G7: home-decor | H7: hero pink | I7: CJ Dropshipping (US warehouse filter) | J7: US (NJ or CA) | K7: Ships from our US warehouse in 4 to 9 business days | L7: Zendrop (Ships From: US filter) | M7: =Margins!H25 -> 33.99 | N7: =Margins!P25 -> 0.4614619 | O7: =Margins!R25 -> 0.31435981 | P7: Pinterest: 'red bow Christmas tree' searches +200% YoY; Etsy: 'velvet Christmas bow set' searches +120% YoY (bow-trend press via snippet, attribution to Ideal Home unconfirmed); Amazon has 5+ pink velvet bow 24-packs live (B0F9WBK2H4, B0H6XXBWHT, B0FPR3H1JF); TikTok Shop 8-pc pink velvet bows listed at $52 (0 sold, pricing gap) | Q7: Bows on the tree is the trend, pink is the version nobody's mom already owns, and 24 wired bows fill a 6 ft tree with no other ornament. | R7: estimate: cost = 40% of the US retail seen (Zendrop guide ratio $8 to $12 product on $25 retail); confirm on cjdropshipping.com
A8: Q07 | B8: Pink velvet bow garland, 6 ft | C8: Q4 | D8: Christmas | E8: the-pink-christmas-tree-edit | F8: The Pink Christmas Tree Edit | G8: home-decor | H8: hero pink | I8: CJ Dropshipping (US warehouse filter) | J8: US (NJ or CA) | K8: Ships from our US warehouse in 4 to 9 business days | L8: Zendrop (Ships From: US filter) | M8: =Margins!H26 -> 35.99 | N8: =Margins!P26 -> 0.45754626 | O8: =Margins!R26 -> 0.31861878 | P8: Same bow-trend signal as Q06 (Pinterest +200% red bow tree, Etsy +120% velvet bow set, via snippet); Pinterest 'Pinkmas decor' and 'Pink holiday aesthetic' idea hubs live (no percentage) | Q8: One garland does the mantel, the banister and the headboard, and it is the shot that gets saved to 'Pinkmas' boards. | R8: estimate: cost = 40% of the US retail seen (Zendrop guide ratio $8 to $12 product on $25 retail); confirm on cjdropshipping.com
A9: Q08 | B9: Pink shatterproof ornament set, 45 pieces | C9: Q4 | D9: Christmas | E9: the-pink-christmas-tree-edit | F9: The Pink Christmas Tree Edit | G9: home-decor | H9: supporting pink (mixed finishes) | I9: CJ Dropshipping (US warehouse filter) | J9: US (NJ or CA) | K9: Ships from our US warehouse in 4 to 9 business days | L9: Zendrop (Ships From: US filter) | M9: =Margins!H27 -> 43.99 | N9: =Margins!P27 -> 0.45340055 | O9: =Margins!R27 -> 0.33973835 | P9: Amazon Best Sellers Christmas Ornaments: VAINECHAY 45-pc pink set surfaced in results (rank not visible in snippet); AliExpress reports 97 results for 'pink christmas ornaments balls' (supply depth only). Weak signal, kept because it completes the tree look. | Q9: Shatterproof means it survives the post office and the dog, and mixed matte, glitter and shiny pink is what makes a tree look styled instead of bought. | R9: estimate: cost = 40% of the US retail seen (Zendrop guide ratio $8 to $12 product on $25 retail); confirm on cjdropshipping.com
A10: Q09 | B10: Pink velvet Christmas stocking with bow | C10: Q4 | D10: Christmas | E10: the-pink-christmas-tree-edit | F10: The Pink Christmas Tree Edit | G10: home-decor | H10: supporting pink | I10: CJ Dropshipping (US warehouse filter) | J10: US (NJ or CA) | K10: Ships from our US warehouse in 4 to 9 business days | L10: Zendrop (Ships From: US filter) | M10: =Margins!H28 -> 26.99 | N10: =Margins!P28 -> 0.46121119 | O10: =Margins!R28 -> 0.27595739 | P10: Amazon 'pink velvet stocking': category shows 100+ bought in past month; BELISHMIE 20-inch 50+; listings at $6.99 to $26.99 with 200+ to 900+ bought (seen in snippet, 27 Sep 2026) https://www.amazon.com/pink-velvet-stocking/s?k=pink+velvet+stocking | Q10: The stocking is the gift-guide crossover: it is decor in the pin and the wrapping for the tumbler in the email. | R10: estimate: cost = 40% of the US retail seen (Zendrop guide ratio $8 to $12 product on $25 retail); confirm on cjdropshipping.com
A11: Q10 | B11: Pink flocked tabletop Christmas tree, 2 ft, unlit | C11: Q4 | D11: Christmas | E11: the-pink-christmas-tree-edit | F11: The Pink Christmas Tree Edit | G11: home-decor | H11: neutral (white flocking on pink) | I11: CJ Dropshipping (US warehouse filter) | J11: US (NJ or CA) | K11: Ships from our US warehouse in 4 to 9 business days | L11: Zendrop (Ships From: US filter) | M11: =Margins!H29 -> 50.99 | N11: =Margins!P29 -> 0.45463993 | O11: =Margins!R29 -> 0.35658149 | P11: Amazon 'pink tinsel christmas tree' and '2ft pink christmas tree': listings show 50+ and 200+ bought in past month (seen in snippet, 27 Sep 2026) https://www.amazon.com/pink-tinsel-tree/s?k=pink+tinsel+tree; TikTok Shop 'pink walmart christmas tree' 11 sold at $189 (weak). Unlit version only (battery-lit trees excluded). | Q11: A 2 ft pink tree is the dorm, desk and apartment answer to 'I have no room for a tree', and it ships in a shoebox. | R11: estimate: cost = 40% of the US retail seen (Zendrop guide ratio $8 to $12 product on $25 retail); confirm on cjdropshipping.com
A12: Q11 | B12: Pink 40 oz insulated tumbler with handle and straw | C12: Q4 | D12: Christmas | E12: pink-gift-guide-stocking-to-new-years-eve | F12: The Pink Gift Guide, Stocking to New Year's Eve | G12: gifts | H12: hero pink | I12: CJ Dropshipping (US warehouse filter) | J12: US (NJ or CA) | K12: Ships from our US warehouse in 4 to 9 business days | L12: Zendrop (Ships From: US filter) | M12: =Margins!H30 -> 43.99 | N12: =Margins!P30 -> 0.45340055 | O12: =Margins!R30 -> 0.33973835 | P12: ASINsight 'pink tumbler with straw' report (mid-2026): #1 ASIN B0D6C6GS58 10K monthly sales, #2 B0CQVWT2NH 8K (+20% MoM), #3 7K (seen in snippet) https://www.asinsight.com/report/US/pink-tumbler-with-straw; CJ Dropshipping carries two 40 oz handle tumbler listings with pink options (agent found URLs on cjdropshipping.com) | Q12: The tumbler is already in every one of her flat lays. Selling the generic pink one herself is the most obvious margin in the bank. | R12: listing found via search; price not visible in snippet, cost is an estimate; confirm on cjdropshipping.com
A13: Q12 | B13: Pink velvet jewelry box with lock | C13: Q4 | D13: Christmas | E13: pink-gift-guide-stocking-to-new-years-eve | F13: The Pink Gift Guide, Stocking to New Year's Eve | G13: gifts | H13: hero pink | I13: CJ Dropshipping (US warehouse filter) | J13: US (NJ or CA) | K13: Ships from our US warehouse in 4 to 9 business days | L13: Zendrop (Ships From: US filter) | M13: =Margins!H31 -> 39.99 | N13: =Margins!P31 -> 0.45088997 | O13: =Margins!R31 -> 0.32585871 | P13: Amazon 'pink jewelry box' 100+ bought in past month; 'pink jewelry gift box' 200+; QBestry velvet box with lock B09SFQ2VGR 50+ (seen in snippet, 27 Sep 2026); TikTok Shop hot-pink jewelry box page $9.99 to $89.99, 'thousands sold' (unverified) | Q13: A velvet box open on the vanity is the definitive 'gift for her' image, and it holds the price point a stocking stuffer can't. | R13: estimate: cost = 40% of the US retail seen (Zendrop guide ratio $8 to $12 product on $25 retail); confirm on cjdropshipping.com
... A41: E24 | B41: Cream hooded wearable blanket | C41: Evergreen | D41: Evergreen | E41: pink-self-care-sunday-the-night-routine | F41: Pink Self-Care Sunday: The Night Routine | G41: home-decor | H41: neutral (cream) | I41: CJ Dropshipping (US warehouse filter) | J41: US (NJ or CA) | K41: Ships from our US warehouse in 4 to 9 business days | L41: Zendrop (Ships From: US filter) | M41: =Margins!H59 -> 43.99 | N41: =Margins!P59 -> 0.45340055 | O41: =Margins!R59 -> 0.33973835 | P41: TikTok Shop keyword page 'pink snuggie blanket': 167 sold at $4.65 deal (seen in snippet, 27 Sep 2026) https://shop.tiktok.com/us/k/pink-snuggie-blanket; Amazon pink faux fur throws 100+ bought in past month (category) | Q41: The cream neutral in a very pink look, and the thing she is actually wearing in the lifestyle photo. | R41: estimate: cost = 40% of the US retail seen (Zendrop guide ratio $8 to $12 product on $25 retail); confirm on cjdropshipping.com

Sheet OrderByDates
A1: Order-by date = holiday date minus (supplier max quoted days + handling days + buffer days), counted in calendar days, then moved back to the previous business day if it lands on a weekend. Carrier cutoffs from search results are listed below the table; the earlier of the two dates wins.
A2: Handling days | B2: 2
A3: Buffer days | B3: 3
A4: Halloween 2026 | B4: 46326
A5: Christmas 2026 | B5: 46381
A6: New Year's Eve 2026 | B6: 46387
A7: Carrier last-ship dates for 25 Dec (from search results; confirm on usps.com, ups.com, fedex.com)
A8: USPS Ground Advantage (contiguous US) | B8: Thu 17 Dec 2026 | C8: https://about.usps.com/newsroom/national-releases/2026/0922-usps-recommends-2026-holiday-mailing-shipping-dates.htm (22 Sep 2026) | D8: seen in snippet
A9: USPS Priority Mail | B9: Fri 18 Dec 2026 | C9: same USPS release (22 Sep 2026) | D9: seen in snippet
A10: USPS Priority Mail Express | B10: Sat 19 Dec 2026 | C10: same USPS release (22 Sep 2026) | D10: seen in snippet
A11: FedEx Ground / Home Delivery | B11: 15 to 19 Dec 2026 by lane | C11: https://www.fedex.com/content/dam/fedex/us-united-states/services/2026_Peak_Last_Day_to_ship.pdf | D11: seen in snippet
A12: FedEx Express Saver / 2Day / Overnight | B12: 21 / 22 / 23 Dec 2026 | C12: same FedEx PDF | D12: seen in snippet
A13: UPS Ground | B13: 16 to 18 Dec (2025 dates; 2026 not published as of 22 Sep 2026) | C13: https://www.ups.com/us/en/support/shipping-support/shipping-services/holiday-shipping-schedule ; 2025 proxy via vesyl.com | D13: 2026 unverified, 2025 used as proxy
A14: UPS 2nd Day Air / Next Day Air | B14: 22 / 23 Dec (2025 proxy) | C14: same | D14: 2026 unverified, 2025 used as proxy
A16: ID | B16: Product | C16: Bank | D16: Winner supplier | E16: Warehouse | F16: Max quoted days | G16: Total lead days | H16: Order by for Halloween | I16: Order by for Christmas | J16: Order by for New Year's Eve | K16: Christmas order-by before 5 Dec? | L16: Q4 status
A17: Q01 | B17: Fluffy pink bunny ears headband | C17: Q4 | D17: CJ Dropshipping (US warehouse filter) | E17: US (NJ or CA) | F17: 9 | G17: =F17+$B$2+$B$3 -> 14 | H17: =WORKDAY($B$4-G17+1,-1) -> 46311 | I17: =WORKDAY($B$5-G17+1,-1) -> 46367 | J17: =WORKDAY($B$6-G17+1,-1) -> 46373 | K17: =IF(I17<DATE(2026,12,5),"YES: not a Christmas product","no") -> no | L17: =IF(F17>=15,"EXCLUDED from Q4 (15+ day quote)",IF(I17<DATE(2026,12,5),"Halloween/BF only","Q4 OK")) -> Q4 OK
A18: Q02 | B18: Pink velvet pumpkins, set of 12 | C18: Q4 | D18: CJ Dropshipping (US warehouse filter) | E18: US (NJ or CA) | F18: 9 | G18: =F18+$B$2+$B$3 -> 14 | H18: =WORKDAY($B$4-G18+1,-1) -> 46311 | I18: =WORKDAY($B$5-G18+1,-1) -> 46367 | J18: =WORKDAY($B$6-G18+1,-1) -> 46373 | K18: =IF(I18<DATE(2026,12,5),"YES: not a Christmas product","no") -> no | L18: =IF(F18>=15,"EXCLUDED from Q4 (15+ day quote)",IF(I18<DATE(2026,12,5),"Halloween/BF only","Q4 OK")) -> Q4 OK
A19: Q03 | B19: Pink faux fur throw blanket, 50 by 60 | C19: Q4 | D19: CJ Dropshipping (US warehouse filter) | E19: US (NJ or CA) | F19: 9 | G19: =F19+$B$2+$B$3 -> 14 | H19: =WORKDAY($B$4-G19+1,-1) -> 46311 | I19: =WORKDAY($B$5-G19+1,-1) -> 46367 | J19: =WORKDAY($B$6-G19+1,-1) -> 46373 | K19: =IF(I19<DATE(2026,12,5),"YES: not a Christmas product","no") -> no | L19: =IF(F19>=15,"EXCLUDED from Q4 (15+ day quote)",IF(I19<DATE(2026,12,5),"Halloween/BF only","Q4 OK")) -> Q4 OK
A20: Q04 | B20: Pink velvet throw pillow covers, pair | C20: Q4 | D20: CJ Dropshipping (US warehouse filter) | E20: US (NJ or CA) | F20: 9 | G20: =F20+$B$2+$B$3 -> 14 | H20: =WORKDAY($B$4-G20+1,-1) -> 46311 | I20: =WORKDAY($B$5-G20+1,-1) -> 46367 | J20: =WORKDAY($B$6-G20+1,-1) -> 46373 | K20: =IF(I20<DATE(2026,12,5),"YES: not a Christmas product","no") -> no | L20: =IF(F20>=15,"EXCLUDED from Q4 (15+ day quote)",IF(I20<DATE(2026,12,5),"Halloween/BF only","Q4 OK")) -> Q4 OK
A21: Q05 | B21: Pink reusable party cups, 16 oz pack | C21: Q4 | D21: CJ Dropshipping (US warehouse filter) | E21: US (NJ or CA) | F21: 9 | G21: =F21+$B$2+$B$3 -> 14 | H21: =WORKDAY($B$4-G21+1,-1) -> 46311 | I21: =WORKDAY($B$5-G21+1,-1) -> 46367 | J21: =WORKDAY($B$6-G21+1,-1) -> 46373 | K21: =IF(I21<DATE(2026,12,5),"YES: not a Christmas product","no") -> no | L21: =IF(F21>=15,"EXCLUDED from Q4 (15+ day quote)",IF(I21<DATE(2026,12,5),"Halloween/BF only","Q4 OK")) -> Q4 OK
A22: Q06 | B22: Pink velvet Christmas tree bows, 24 pack | C22: Q4 | D22: CJ Dropshipping (US warehouse filter) | E22: US (NJ or CA) | F22: 9 | G22: =F22+$B$2+$B$3 -> 14 | H22: =WORKDAY($B$4-G22+1,-1) -> 46311 | I22: =WORKDAY($B$5-G22+1,-1) -> 46367 | J22: =WORKDAY($B$6-G22+1,-1) -> 46373 | K22: =IF(I22<DATE(2026,12,5),"YES: not a Christmas product","no") -> no | L22: =IF(F22>=15,"EXCLUDED from Q4 (15+ day quote)",IF(I22<DATE(2026,12,5),"Halloween/BF only","Q4 OK")) -> Q4 OK
A23: Q07 | B23: Pink velvet bow garland, 6 ft | C23: Q4 | D23: CJ Dropshipping (US warehouse filter) | E23: US (NJ or CA) | F23: 9 | G23: =F23+$B$2+$B$3 -> 14 | H23: =WORKDAY($B$4-G23+1,-1) -> 46311 | I23: =WORKDAY($B$5-G23+1,-1) -> 46367 | J23: =WORKDAY($B$6-G23+1,-1) -> 46373 | K23: =IF(I23<DATE(2026,12,5),"YES: not a Christmas product","no") -> no | L23: =IF(F23>=15,"EXCLUDED from Q4 (15+ day quote)",IF(I23<DATE(2026,12,5),"Halloween/BF only","Q4 OK")) -> Q4 OK
A24: Q08 | B24: Pink shatterproof ornament set, 45 pieces | C24: Q4 | D24: CJ Dropshipping (US warehouse filter) | E24: US (NJ or CA) | F24: 9 | G24: =F24+$B$2+$B$3 -> 14 | H24: =WORKDAY($B$4-G24+1,-1) -> 46311 | I24: =WORKDAY($B$5-G24+1,-1) -> 46367 | J24: =WORKDAY($B$6-G24+1,-1) -> 46373 | K24: =IF(I24<DATE(2026,12,5),"YES: not a Christmas product","no") -> no | L24: =IF(F24>=15,"EXCLUDED from Q4 (15+ day quote)",IF(I24<DATE(2026,12,5),"Halloween/BF only","Q4 OK")) -> Q4 OK
A25: Q09 | B25: Pink velvet Christmas stocking with bow | C25: Q4 | D25: CJ Dropshipping (US warehouse filter) | E25: US (NJ or CA) | F25: 9 | G25: =F25+$B$2+$B$3 -> 14 | H25: =WORKDAY($B$4-G25+1,-1) -> 46311 | I25: =WORKDAY($B$5-G25+1,-1) -> 46367 | J25: =WORKDAY($B$6-G25+1,-1) -> 46373 | K25: =IF(I25<DATE(2026,12,5),"YES: not a Christmas product","no") -> no | L25: =IF(F25>=15,"EXCLUDED from Q4 (15+ day quote)",IF(I25<DATE(2026,12,5),"Halloween/BF only","Q4 OK")) -> Q4 OK
A26: Q10 | B26: Pink flocked tabletop Christmas tree, 2 ft, unlit | C26: Q4 | D26: CJ Dropshipping (US warehouse filter) | E26: US (NJ or CA) | F26: 9 | G26: =F26+$B$2+$B$3 -> 14 | H26: =WORKDAY($B$4-G26+1,-1) -> 46311 | I26: =WORKDAY($B$5-G26+1,-1) -> 46367 | J26: =WORKDAY($B$6-G26+1,-1) -> 46373 | K26: =IF(I26<DATE(2026,12,5),"YES: not a Christmas product","no") -> no | L26: =IF(F26>=15,"EXCLUDED from Q4 (15+ day quote)",IF(I26<DATE(2026,12,5),"Halloween/BF only","Q4 OK")) -> Q4 OK
A27: Q11 | B27: Pink 40 oz insulated tumbler with handle and straw | C27: Q4 | D27: CJ Dropshipping (US warehouse filter) | E27: US (NJ or CA) | F27: 9 | G27: =F27+$B$2+$B$3 -> 14 | H27: =WORKDAY($B$4-G27+1,-1) -> 46311 | I27: =WORKDAY($B$5-G27+1,-1) -> 46367 | J27: =WORKDAY($B$6-G27+1,-1) -> 46373 | K27: =IF(I27<DATE(2026,12,5),"YES: not a Christmas product","no") -> no | L27: =IF(F27>=15,"EXCLUDED from Q4 (15+ day quote)",IF(I27<DATE(2026,12,5),"Halloween/BF only","Q4 OK")) -> Q4 OK
A28: Q12 | B28: Pink velvet jewelry box with lock | C28: Q4 | D28: CJ Dropshipping (US warehouse filter) | E28: US (NJ or CA) | F28: 9 | G28: =F28+$B$2+$B$3 -> 14 | H28: =WORKDAY($B$4-G28+1,-1) -> 46311 | I28: =WORKDAY($B$5-G28+1,-1) -> 46367 | J28: =WORKDAY($B$6-G28+1,-1) -> 46373 | K28: =IF(I28<DATE(2026,12,5),"YES: not a Christmas product","no") -> no | L28: =IF(F28>=15,"EXCLUDED from Q4 (15+ day quote)",IF(I28<DATE(2026,12,5),"Halloween/BF only","Q4 OK")) -> Q4 OK
... A56: E24 | B56: Cream hooded wearable blanket | C56: Evergreen | D56: CJ Dropshipping (US warehouse filter) | E56: US (NJ or CA) | F56: 9 | G56: =F56+$B$2+$B$3 -> 14 | H56: =WORKDAY($B$4-G56+1,-1) -> 46311 | I56: =WORKDAY($B$5-G56+1,-1) -> 46367 | J56: =WORKDAY($B$6-G56+1,-1) -> 46373 | K56: =IF(I56<DATE(2026,12,5),"YES: not a Christmas product","no") -> no | L56: =IF(F56>=15,"EXCLUDED from Q4 (15+ day quote)",IF(I56<DATE(2026,12,5),"Halloween/BF only","Q4 OK")) -> Q4 OK
